Workbook

Sheet ראשי
A2: 1. בחר מאגר דפאות/תרחישים עבור הסקר. ניתן להיעזר בגיליונות שבמסמך זה או במאגר חלופי
A3: 2. הגדר מתוך כלל האיומים והתרחישים, את האיומים לייחוס
A4: 3. עבור כל איום, הגדר סבירות ועוצמה
A5: 4. הגדר אופן טיפול באיומים בהתאם לתיאבון הסיכון
A6: 5. הגדר בקרות מפצות וצעדים נוספים להפחתת הסיכון מתוך גיליון בקרות, או מתוך מאגר בקרות חלופי

Sheet דפאות בסיסי
A1: מקור | B1: תיאור | C1: הממשק
A2: איום פנימי | B2: שליחת הודעת דוא"ל עם מידע ארגוני לגורם לא מורשה | C2: דוא"ל
A3: איום פנימי | B3: טעינת קובץ עם מידע ארגוני לאתר חיצוני שאינו מורשה (דוא"ל, BOX וכו') | C3: גישה לאינטרנט
A4: איום פנימי | B4: העתקה ללא רשות של מידע ארגוני להתקן חיצוני (לרבות קוד מקור) | C4: התקן חיצוני (DOK, CD etc.)
A5: איום פנימי | B5: גישה למידע ארגוני (דיגיטלי/פיזי) ללא רשות | C5: גישה פיזית או גישה רשתית (כגון גישה מרחוק או שיטוט בתיקיות רשת)
A6: איום פנימי | B6: התקנת תוכנה לא מורשית / תוכנה עם נוזקה | C6: עמדת עבודה, גישה רשתית
A7: איום פנימי | B7: חשיפת מידע ארגוני בפני לא מורשה (פישינג, שיחת חולין וכו') | C7: גישה לאינטרנט, גישה פיזית
A8: איום פנימי | B8: חיבור התקן חיצוני עם נוזקה לרשת הארגון | C8: התקן חיצוני (דוגמת DOK, CD)
A9: איום פנימי | B9: מחיקה/שיבוש/מניעת גישה למידע ארגוני | C9: עמדת עבודה, גישה רשתית
A10: איום פנימי | B10: גניבה פיסית או אובדן של התקן/רכיב מחשוב | C10: גישה פיזית
A11: איום פנימי | B11: גניבה פיסית או אובדן של מסמך מודפס המכיל מידע ארגוני | C11: גישה פיזית
A12: איום חיצוני | B12: מניעת שירות במבואות האינטרנט של הארגון | C12: גישה לאינטרנט
... A34: שרשרת אספקה | B34: פיתוח מוצר תוכנה עבור הארגון המכיל חולשות מהותיות המנוצלות לרעה (דוגמת Back door) | C34: גישה רשתית

Sheet דפאות מורחב
A1: חלופה בסיסית | B1: משפחה/דפ"א | C1: תת משפחה/דפ"א | D1: האיום | E1: אופן מימוש | F1: ממשק ביצוע | G1: קושי מימוש התרחיש 1(H)-2(M)-3(L) | H1: מידת נפוצות התרחיש 1(L)-2(M)-3(H) | I1: חלופה מתקדמת | J1: # | K1: =IFERROR(__xludf.DUMMYFUNCTION("GOOGLETRANSLATE(B2, ""auto"", ""en"")"),"Name UBI") -> Name UBI | L1: =IFERROR(__xludf.DUMMYFUNCTION("GOOGLETRANSLATE(D2, ""auto"", ""en"")"),"Description") -> Description | M1: =IFERROR(__xludf.DUMMYFUNCTION("GOOGLETRANSLATE(F2, ""auto"", ""en"")"),"Source threat (characteristics and potential of the offender)") -> Source threat (characteristics and potential of the offender) | N1: =IFERROR(__xludf.DUMMYFUNCTION("GOOGLETRANSLATE(H2, ""auto"", ""en"")"),"the impact of an object") -> the impact of an object
B2: מחשוב ענן ציבורי | C2: ניצול הרשאות עובד פנימי/חיצוני | D2: איום חיצוני/שרשרת אספקה | E2: ניצול שירותי ענן חיצונים של החברה על מנת להוציא מידע סודי וזאת ע"י עובדי ספק הענן עצמו ואו באמצעותם | F2: גישה מרחוק, גישה רשתית | G2: 2 | H2: 2 | J2: 1 | K2: =IFERROR(__xludf.DUMMYFUNCTION("GOOGLETRANSLATE(B3, ""auto"", ""en"")"),"The threat of the automatic propagation of malicious code into a grid system") -> The threat of the automatic propagation of malicious code into a grid system | L2: =IFERROR(__xludf.DUMMYFUNCTION("GOOGLETRANSLATE(D3, ""auto"", ""en"")"),"The threat is the ability to implement and run malicious code on behalf of a trusted process in any of the resource grid system of centers and its automatic extension to all nodes of grid system. This threat is caused by weakness of grid computing techno"&"logy - a high level of automation at low manageability grid system. Implementation of this threat can be provided that the offender is a legal privilege user grid system") -> The threat is the ability to implement and run malicious code on behalf of a trusted process in any of the resource grid system of centers and its automatic extension to all nodes of grid system. This threat is caused by weakness of grid computing technology - a high level of automation at low manageability grid system. Implementation of this threat can be provided that the offender is a legal privilege user grid system | M2: =IFERROR(__xludf.DUMMYFUNCTION("GOOGLETRANSLATE(F3, ""auto"", ""en"")"),"External intruder with an average potential intruder inner middle potential") -> External intruder with an average potential intruder inner middle potential | N2: =IFERROR(__xludf.DUMMYFUNCTION("GOOGLETRANSLATE(H3, ""auto"", ""en"")"),"Resource Centers grid system") -> Resource Centers grid system
B3: הגנה על המידע | C3: אגירת מידע רגיש | D3: איום פנימי | E3: שליחת מידע עסקי (תכניות אסטרטגיות, סודות מסחריים, גורמים חיצוניים, לקוחות, שותפים עסקיים וכו') לכתובת מייל פרטית | F3: גישה לאינטרנט (גלישה, דוא"ל וכו') | G3: 3 | H3: 3 | J3: 2 | K3: =IFERROR(__xludf.DUMMYFUNCTION("GOOGLETRANSLATE(B4, ""auto"", ""en"")"),"The threat of aggregating data transmitted in the Grid System") -> The threat of aggregating data transmitted in the Grid System | L3: =IFERROR(__xludf.DUMMYFUNCTION("GOOGLETRANSLATE(D4, ""auto"", ""en"")"),"The threat is the possibility of the disclosure of information protected by intruder detection involved in its processing units, data collection, analysis and synthesis of data intercepted by the data transmission network grid system. This threat is caus"&"ed by the weakness of grid computing technology - the use of unprotected Internet channel as a transport network grid system. Implementation of this threat can be provided that the offender: forces and sufficient funds to compensate for the distributed "&"emergency Grid assignments between nodes grid system; privileges sufficient to intercept the data traffic between the network elements (nodes) grid system") -> The threat is the possibility of the disclosure of information protected by intruder detection involved in its processing units, data collection, analysis and synthesis of data intercepted by the data transmission network grid system. This threat is caused by the weakness of grid computing technology - the use of unprotected Internet channel as a transport network grid system. Implementation of this threat can be provided that the offender: forces and sufficient funds to compensate for the distributed emergency Grid assignments between nodes grid system; privileges sufficient to intercept the data traffic between the network elements (nodes) grid system | M3: =IFERROR(__xludf.DUMMYFUNCTION("GOOGLETRANSLATE(F4, ""auto"", ""en"")"),"The outer middle potential violator") -> The outer middle potential violator | N3: =IFERROR(__xludf.DUMMYFUNCTION("GOOGLETRANSLATE(H4, ""auto"", ""en"")"),"network traffic") -> network traffic
B4: הגנת תחנות עבודה ושרתים | C4: חדירה מהאינטרנט ישירות לרשת הארגון | D4: איום פנימי/חיצוני | E4: חיבור ציוד מחשב לעמדת קצה ואו לעמדה/רשת מבודלת עם רגל החוצה לאינטרנט באמצעות: הקמת HOT SPOT ואו רשת אלחוטית | F4: התקן חיצוני (דוגמת LAPTOP, WIFI) | G4: 3 | H4: 3 | J4: 3 | K4: =IFERROR(__xludf.DUMMYFUNCTION("GOOGLETRANSLATE(B5, ""auto"", ""en"")"),"cryptographic algorithms to analyze the threat and their implementation") -> cryptographic algorithms to analyze the threat and their implementation | L4: =IFERROR(__xludf.DUMMYFUNCTION("GOOGLETRANSLATE(D5, ""auto"", ""en"")"),"The threat is the ability to identify weaknesses in the cryptographic algorithms, or vulnerabilities in the software that implements them. This threat is due to weaknesses of cryptographic algorithms, as well as errors in the program code of cryptographi"&"c tools, their conjugation with the system or their settings. Implementation of the threat is possible in the case of the offender information on the means used in the encryption system implemented in their encryption algorithms and their settings") -> The threat is the ability to identify weaknesses in the cryptographic algorithms, or vulnerabilities in the software that implements them. This threat is due to weaknesses of cryptographic algorithms, as well as errors in the program code of cryptographic tools, their conjugation with the system or their settings. Implementation of the threat is possible in the case of the offender information on the means used in the encryption system implemented in their encryption algorithms and their settings | M4: =IFERROR(__xludf.DUMMYFUNCTION("GOOGLETRANSLATE(F5, ""auto"", ""en"")"),"The outer middle potential violator") -> The outer middle potential violator | N4: =IFERROR(__xludf.DUMMYFUNCTION("GOOGLETRANSLATE(H5, ""auto"", ""en"")"),"Metadata, system software") -> Metadata, system software
B5: הגנה על המידע | C5: אגירת מידע רגיש | D5: איום פנימי | E5: אגירת המידע טרם הזלגתו - במערכת, ברשומות, במדיה חיצונית | F5: התקן חיצוני (דוגמת DOK, CD) | G5: 3 | H5: 2 | J5: 4 | K5: =IFERROR(__xludf.DUMMYFUNCTION("GOOGLETRANSLATE(B6, ""auto"", ""en"")"),"Threat hardware reset BIOS password") -> Threat hardware reset BIOS password | L5: =IFERROR(__xludf.DUMMYFUNCTION("GOOGLETRANSLATE(D6, ""auto"", ""en"")"),"The threat is reset passwords capabilities installed in BIOS / UEFI without passing authorization procedure in the system by de-energizing BIOS chip (accumulator material removal) or install jumpers in the normal place on the system board (switch ""jumper"&"""). This threat is due to some system vulnerabilities (parent) boards - the presence of hard reset passwords mechanisms installed in BIOS / UEFI. Implementation of this threat is possible on condition that the intruder physical access to the computer s"&"ystem unit") -> The threat is reset passwords capabilities installed in BIOS / UEFI without passing authorization procedure in the system by de-energizing BIOS chip (accumulator material removal) or install jumpers in the normal place on the system board (switch "jumper"). This threat is due to some system vulnerabilities (parent) boards - the presence of hard reset passwords mechanisms installed in BIOS / UEFI. Implementation of this threat is possible on condition that the intruder physical access to the computer system unit | M5: =IFERROR(__xludf.DUMMYFUNCTION("GOOGLETRANSLATE(F6, ""auto"", ""en"")"),"Insider with a low potential") -> Insider with a low potential | N5: =IFERROR(__xludf.DUMMYFUNCTION("GOOGLETRANSLATE(H6, ""auto"", ""en"")"),"Firmware and BIOS / UEFI hardware") -> Firmware and BIOS / UEFI hardware
B6: הגנה על המידע | C6: ניצול הרשאות עובד פנימי/חיצוני | D6: שרשרת אספקה | E6: שימוש בתהליך לגיטימי של מערכת מחשב שמוציא מידע החוצה לאינטרנט ועליו לייצא מידע נוסף שאינו רלוונטי לפעולה הנדרשת | F6: גישה לאינטרנט | G6: 1 | H6: 1 | J6: 5 | K6: =IFERROR(__xludf.DUMMYFUNCTION("GOOGLETRANSLATE(B7, ""auto"", ""en"")"),"The threat of malicious code in the BIOS") -> The threat of malicious code in the BIOS | L6: =IFERROR(__xludf.DUMMYFUNCTION("GOOGLETRANSLATE(D7, ""auto"", ""en"")"),"The threat is the ability to make the BIOS / UEFI execute malicious code each time the computer is started by introducing it into the BIOS / UEFI chips by replacing BIOS / UEFI or update BIOS / UEFI software to a version that already contains malicious co"&"de. This threat is due to the weaknesses of control technologies for updating BIOS / UEFI software and BIOS / UEFI replacement chipset. Implementation of this threat is possible in the course of repair and computer maintenance") -> The threat is the ability to make the BIOS / UEFI execute malicious code each time the computer is started by introducing it into the BIOS / UEFI chips by replacing BIOS / UEFI or update BIOS / UEFI software to a version that already contains malicious code. This threat is due to the weaknesses of control technologies for updating BIOS / UEFI software and BIOS / UEFI replacement chipset. Implementation of this threat is possible in the course of repair and computer maintenance | M6: =IFERROR(__xludf.DUMMYFUNCTION("GOOGLETRANSLATE(F7, ""auto"", ""en"")"),"Insider with high potential") -> Insider with high potential | N6: =IFERROR(__xludf.DUMMYFUNCTION("GOOGLETRANSLATE(H7, ""auto"", ""en"")"),"Firmware and BIOS / UEFI hardware") -> Firmware and BIOS / UEFI hardware
B7: אבטחת רשת | C7: ניצול הרשאות עובד פנימי/חיצוני | D7: איום פנימי | E7: התקנה ושימוש בתוכנות שיתוף קבצים | F7: גישה לאינטרנט | G7: 3 | H7: 2 | J7: 6 | K7: =IFERROR(__xludf.DUMMYFUNCTION("GOOGLETRANSLATE(B8, ""auto"", ""en"")"),"code injection, or threat data") -> code injection, or threat data | L7: =IFERROR(__xludf.DUMMYFUNCTION("GOOGLETRANSLATE(D8, ""auto"", ""en"")"),"The threat is the possibility of the introduction of the offender in diskreditiruemuyu information or IoT-device malicious code, which can be launched in the future ""by hand"" users automatically when performing certain conditions (occurrence of a certai"&"n date, user logon, etc.) or using the authentication data set ""by default"", as well as the possibility of the introduction of unauthorized intruder some proprietary data to be processed in an information system diskreditiruemuyu actually having carried"&" out the illegal use of other people's computer resources, and block devices work when certain commands. This threat is caused by: presence of software vulnerabilities; weaknesses measures antivirus and access control; Telnet-presence of open ports on"&" IoT-device (for IoT-devices). The implementation of this possible threat: in the case of diskreditiruemogo user with files coming from untrusted sources; if he has privileges install the software; in the case of unmodified owner credentials IoT-devic"&"e (factory password and login)") -> The threat is the possibility of the introduction of the offender in diskreditiruemuyu information or IoT-device malicious code, which can be launched in the future "by hand" users automatically when performing certain conditions (occurrence of a certain date, user logon, etc.) or using the authentication data set "by default", as well as the possibility of the introduction of unauthorized intruder some proprietary data to be processed in an information system diskreditiruemuyu actually having carried out the illegal use of other people's computer resources, and block devices work when certain commands. This threat is caused by: presence of software vulnerabilities; weaknesses measures antivirus and access control; Telnet-presence of open ports on IoT-device (for IoT-devices). The implementation of this possible threat: in the case of diskreditiruemogo user with files coming from untrusted sources; if he has privileges install the software; in the case of unmodified owner credentials IoT-device (factory password and login) | M7: =IFERROR(__xludf.DUMMYFUNCTION("GOOGLETRANSLATE(F8, ""auto"", ""en"")"),"External intruder with a low potential") -> External intruder with a low potential | N7: =IFERROR(__xludf.DUMMYFUNCTION("GOOGLETRANSLATE(H8, ""auto"", ""en"")"),"System software, application software, networking software") -> System software, application software, networking software
B8: הגנה על המידע | C8: רשלנות מקצועית | D8: איום פנימי | E8: איבוד/הוצאה של מדיה, רשומות פיזיות ורכיבי מחשוב עם מידע מסווג, אל מחוץ למתקן והגעתם אל גורם עוין | F8: גישה פיזית | G8: 3 | H8: 3 | J8: 7 | K8: =IFERROR(__xludf.DUMMYFUNCTION("GOOGLETRANSLATE(B9, ""auto"", ""en"")"),"The threat of exposure to the program with high privileges") -> The threat of exposure to the program with high privileges | L8: =IFERROR(__xludf.DUMMYFUNCTION("GOOGLETRANSLATE(D9, ""auto"", ""en"")"),"The threat is the possibility of increasing the offender of their privileges in the discredited system (getting discredited programs privileges) through the use of bugs in the programs and execute arbitrary code with their privileges. This threat is caus"&"ed by input validation weaknesses mechanism and teams, as well as the delimitation of access measures. Implementation of this threat is possible under the conditions: possession diskreditiruemoy program elevated privileges on the system; diskreditiruem"&"oy of the program receiving input from other programs or from the user; the offender is able to transmit data to the program diskreditiruemoy") -> The threat is the possibility of increasing the offender of their privileges in the discredited system (getting discredited programs privileges) through the use of bugs in the programs and execute arbitrary code with their privileges. This threat is caused by input validation weaknesses mechanism and teams, as well as the delimitation of access measures. Implementation of this threat is possible under the conditions: possession diskreditiruemoy program elevated privileges on the system; diskreditiruemoy of the program receiving input from other programs or from the user; the offender is able to transmit data to the program diskreditiruemoy | M8: =IFERROR(__xludf.DUMMYFUNCTION("GOOGLETRANSLATE(F9, ""auto"", ""en"")"),"External intruder with an average potential intruder inner middle potential") -> External intruder with an average potential intruder inner middle potential | N8: =IFERROR(__xludf.DUMMYFUNCTION("GOOGLETRANSLATE(H9, ""auto"", ""en"")"),"Information system, virtual machine, network software, network traffic") -> Information system, virtual machine, network software, network traffic
B9: הגנה על המידע | C9: רשלנות מקצועית | D9: שרשרת אספקה | E9: הוצאה של רשומות גרוסות עם מידע מסווג, אל מחוץ למתקן והגעתם אל גורם עוין | F9: גישה פיזית | G9: 3 | H9: 2 | J9: 8 | K9: =IFERROR(__xludf.DUMMYFUNCTION("GOOGLETRANSLATE(B10, ""auto"", ""en"")"),"The threat of recovery and / or reuse of the authentication information") -> The threat of recovery and / or reuse of the authentication information | L9: =IFERROR(__xludf.DUMMYFUNCTION("GOOGLETRANSLATE(D10, ""auto"", ""en"")"),"The threat lies in the possibility of access to user data as a result of the selection (e.g. by exhaustive search or sorting dictionary) diskreditiruemoy authentication information with the user account in the system, as well as by intercepting and re-use"&" password hash to recover the session. This threat is due to the following disadvantages: much smaller volume of data authentication information hash code compared with itself (the time of selection of the hash codes is less than the exhaustive search t"&"ime of authentication information); weaknesses in the algorithm for calculating a hash code, prevent its re-use to perform a successful authentication. Implementation of this threat is possible with the help of special software, and in some cases - ""ma"&"nually""") -> The threat lies in the possibility of access to user data as a result of the selection (e.g. by exhaustive search or sorting dictionary) diskreditiruemoy authentication information with the user account in the system, as well as by intercepting and re-use password hash to recover the session. This threat is due to the following disadvantages: much smaller volume of data authentication information hash code compared with itself (the time of selection of the hash codes is less than the exhaustive search time of authentication information); weaknesses in the algorithm for calculating a hash code, prevent its re-use to perform a successful authentication. Implementation of this threat is possible with the help of special software, and in some cases - "manually" | M9: =IFERROR(__xludf.DUMMYFUNCTION("GOOGLETRANSLATE(F10, ""auto"", ""en"")"),"External intruder low potential insider with a low potential") -> External intruder low potential insider with a low potential | N9: =IFERROR(__xludf.DUMMYFUNCTION("GOOGLETRANSLATE(H10, ""auto"", ""en"")"),"System software, firmware, usernames user data") -> System software, firmware, usernames user data
B10: הגנה פיזית וסביבתית | C10: הנדסה חברתית לעובד פנימי/חיצוני | D10: איום פנימי/חיצוני | E10: שיטוי והתקנת רכיבי ריגול במתחם מסווג באמצעות הטמנת אמצעי האזנה/הקלטה/שידור | F10: גישה פיזית | G10: 1 | H10: 1 | J10: 9 | K10: =IFERROR(__xludf.DUMMYFUNCTION("GOOGLETRANSLATE(B11, ""auto"", ""en"")"),"Threat to restore the previous version of the BIOS vulnerable") -> Threat to restore the previous version of the BIOS vulnerable | L10: =IFERROR(__xludf.DUMMYFUNCTION("GOOGLETRANSLATE(D11, ""auto"", ""en"")"),"The threat lies in the possibility of the use of the stimulated transition BIOS / UEFI, comprising vulnerability. This threat is due to the weaknesses of control technologies for updating BIOS / UEFI software. When using the BIOS / UEFI technology updat"&"es, you may experience the following situation (conditions that characterize the situation listed in chronological order): the computer is running some version of BIOS / UEFI, for which at the time of its operation are not known vulnerabilities; due to "&"certain BIOS / UEFI circumstances runs the update process by maintaining the previous BIOS / UEFI version in the case of a ""rollback"" of the system; published data on the existence of vulnerabilities in previous versions of BIOS / UEFI; malfunction oc"&"curs in the system, whereby the current (new) version of the BIOS / UEFI becomes inoperative (e.g., its integrity is violated); the user carries out a full-time system recovery procedure - conducting a ""rollback"" of the system to a previous working sta"&"te") -> The threat lies in the possibility of the use of the stimulated transition BIOS / UEFI, comprising vulnerability. This threat is due to the weaknesses of control technologies for updating BIOS / UEFI software. When using the BIOS / UEFI technology updates, you may experience the following situation (conditions that characterize the situation listed in chronological order): the computer is running some version of BIOS / UEFI, for which at the time of its operation are not known vulnerabilities; due to certain BIOS / UEFI circumstances runs the update process by maintaining the previous BIOS / UEFI version in the case of a "rollback" of the system; published data on the existence of vulnerabilities in previous versions of BIOS / UEFI; malfunction occurs in the system, whereby the current (new) version of the BIOS / UEFI becomes inoperative (e.g., its integrity is violated); the user carries out a full-time system recovery procedure - conducting a "rollback" of the system to a previous working state | M10: =IFERROR(__xludf.DUMMYFUNCTION("GOOGLETRANSLATE(F11, ""auto"", ""en"")"),"Insider with a low potential") -> Insider with a low potential | N10: =IFERROR(__xludf.DUMMYFUNCTION("GOOGLETRANSLATE(H11, ""auto"", ""en"")"),"BIOS / UEFI firmware") -> BIOS / UEFI firmware
B11: אבטחה ברכש ופיתוח | C11: חבלה בשרשרת אספקה | D11: איום פנימי/חיצוני | E11: התקנת/החלפת מוצר/ציוד המוגדר כ"מטופל" ע"י גורם פנימי ואו חיצוני - לצרכי האזנה או לחדירה מרחוק לרשת, חוסר מודעות, רשלנות מקצועית, חוסר משמעת ואו עובד ממורמר. ה"טיפול" יכול להתבצע לאורך כל שרשרת האספקה ואו התפעול: פיתוח, ייצור, משלוח, המתנה אצל ספק משנה, התקנה בלקוח, עדכוני חתימות, מפתחות הצפנה ותוכנה, תחזוקה, שליחה לתיקון וביצוע מבדקים (חדירה, פגיעויות, פורנזיקה וביקורת) | F11: גישה פיזית, גישה רשתית, גישה מרחוק | G11: 3 | H11: 2 | J11: 10 | K11: =IFERROR(__xludf.DUMMYFUNCTION("GOOGLETRANSLATE(B12, ""auto"", ""en"")"),"process exit threat of the virtual machine") -> process exit threat of the virtual machine | L11: =IFERROR(__xludf.DUMMYFUNCTION("GOOGLETRANSLATE(D12, ""auto"", ""en"")"),"The threat is the ability to run the malicious program's own hypervisor, operating on the level of logical interaction below being compromised hypervisor. This threat is caused by software vulnerabilities hypervisor that implements the function of the sa"&"ndbox for operating in its programs, as well as weaknesses in hardware support for virtualization at the processor level instructions. Implementation of this threat leads not only to compromise the hypervisor, but running in a virtual environment created"&" by him protection and, consequently, to their inability to perform security functions for malware, operating under the control of its own hypervisor") -> The threat is the ability to run the malicious program's own hypervisor, operating on the level of logical interaction below being compromised hypervisor. This threat is caused by software vulnerabilities hypervisor that implements the function of the sandbox for operating in its programs, as well as weaknesses in hardware support for virtualization at the processor level instructions. Implementation of this threat leads not only to compromise the hypervisor, but running in a virtual environment created by him protection and, consequently, to their inability to perform security functions for malware, operating under the control of its own hypervisor | M11: =IFERROR(__xludf.DUMMYFUNCTION("GOOGLETRANSLATE(F12, ""auto"", ""en"")"),"External intruder with an average potential intruder inner middle potential") -> External intruder with an average potential intruder inner middle potential | N11: =IFERROR(__xludf.DUMMYFUNCTION("GOOGLETRANSLATE(H12, ""auto"", ""en"")"),"Information System, a network node, the media, the file system object, Accounts user data, virtual machine image") -> Information System, a network node, the media, the file system object, Accounts user data, virtual machine image
B12: הגנה על המידע | C12: רשלנות מקצועית | D12: איום פנימי | E12: ציתות לשיחות קוליות מסווגות בשל קירבה פיזית ואו בזמן ששיחה טלפונית אחרת מתקיימת ברקע | F12: גישה פיזית, גישה טלפונית | G12: 3 | H12: 2 | J12: 11 | K12: =IFERROR(__xludf.DUMMYFUNCTION("GOOGLETRANSLATE(B13, ""auto"", ""en"")"),"Threat deauthorize authorized wireless client") -> Threat deauthorize authorized wireless client | L12: =IFERROR(__xludf.DUMMYFUNCTION("GOOGLETRANSLATE(D13, ""auto"", ""en"")"),"The threat is the possibility of automatic disconnection of the wireless access point to authorized wireless client. This threat is caused by the weakness of networking technology for wireless data communication channels - information about the MAC addre"&"sses of wireless clients available to all participants in networking. Implementation of this threat can be provided to connect the violator to a wireless network device, the MAC address will be the same as the MAC address of the client's authorized diskr"&"editiruemogo") -> The threat is the possibility of automatic disconnection of the wireless access point to authorized wireless client. This threat is caused by the weakness of networking technology for wireless data communication channels - information about the MAC addresses of wireless clients available to all participants in networking. Implementation of this threat can be provided to connect the violator to a wireless network device, the MAC address will be the same as the MAC address of the client's authorized diskreditiruemogo | M12: =IFERROR(__xludf.DUMMYFUNCTION("GOOGLETRANSLATE(F13, ""auto"", ""en"")"),"External intruder low potential insider with a low potential") -> External intruder low potential insider with a low potential | N12: =IFERROR(__xludf.DUMMYFUNCTION("GOOGLETRANSLATE(H13, ""auto"", ""en"")"),"The network node") -> The network node
B13: הגנה פיזית וסביבתית | C13: ניצול הרשאות עובד פנימי/חיצוני | D13: איום חיצוני/שרשרת אספקה | E13: נגישות לנקודה חמה ואו תווך/ציוד תקשורת אשר אליו מחוברות מערכות הארגון ופתיחת קו החוצה | F13: גישה פיזית, גישה רשתית | G13: 2 | H13: 3 | J13: 12 | K13: =IFERROR(__xludf.DUMMYFUNCTION("GOOGLETRANSLATE(B14, ""auto"", ""en"")"),"The threat of a destructive change of configuration / programming environment protection") -> The threat of a destructive change of configuration / programming environment protection | L13: =IFERROR(__xludf.DUMMYFUNCTION("GOOGLETRANSLATE(D14, ""auto"", ""en"")"),"The threat is the possibility of a destructive impact on the software application diskreditiruemoe way of manipulation with the configuration files or libraries used them. This threat is caused by weakness of integrity controls configuration files or lib"&"raries used by applications. Implementation of this threat is possible in the case of the infringer of the rights of the entries in the file objects associated with the configuration / software environment environment, or the ability to redirect requests"&" from the program diskreditiruemoy protected file object to false") -> The threat is the possibility of a destructive impact on the software application diskreditiruemoe way of manipulation with the configuration files or libraries used them. This threat is caused by weakness of integrity controls configuration files or libraries used by applications. Implementation of this threat is possible in the case of the infringer of the rights of the entries in the file objects associated with the configuration / software environment environment, or the ability to redirect requests from the program diskreditiruemoy protected file object to false | M13: =IFERROR(__xludf.DUMMYFUNCTION("GOOGLETRANSLATE(F14, ""auto"", ""en"")"),"Insider with a low potential") -> Insider with a low potential | N13: =IFERROR(__xludf.DUMMYFUNCTION("GOOGLETRANSLATE(H14, ""auto"", ""en"")"),"System software, application software, network software, firmware, metadata, file system objects, the registry") -> System software, application software, network software, firmware, metadata, file system objects, the registry
B14: הגנת תחנות עבודה ושרתים | C14: ניצול הרשאות עובד פנימי/חיצוני | D14: איום פנימי/חיצוני | E14: נגישות לעמדת קצה של משתמש (כולל מכשיר סלולרי) והתקנת כלי הסנפה/תקיפה/השתלטות ואו הטמנת קוד, שינוי הגדרות מערכת, שאיבת מידע עם מדיה חיצונית ואו שימוש בהרשאות הלגיטימיות של המשתמש במערכות הארגון ואו ליצור חשבונות נוספים כדי לחדור למערכות. במידה והעמדה אינה מחוברת לאינטרנט תיתכן התקנת ACCESS POINT והמשך דפ"א בהתאם לעיל | F14: גישה פיזית, גישה רשתית, גישה מרחוק | G14: 2 | H14: 3 | J14: 13 | K14: =IFERROR(__xludf.DUMMYFUNCTION("GOOGLETRANSLATE(B15, ""auto"", ""en"")"),"The threat of a destructive use of the declared functional BIOS") -> The threat of a destructive use of the declared functional BIOS | L14: =IFERROR(__xludf.DUMMYFUNCTION("GOOGLETRANSLATE(D15, ""auto"", ""en"")"),"The threat is the possibility of misuse declared BIOS / UEFI functional for violating the integrity of the information stored in the external storage media and a random access memory computer. This threat is caused by vulnerabilities BIOS / UEFI software"&" designed for testing and computer maintenance (funds check memory integrity, software RAID-controller management software, etc.). Realization of this threat may contribute to the ability to update some of the BIOS / UEFI without passing authentication") -> The threat is the possibility of misuse declared BIOS / UEFI functional for violating the integrity of the information stored in the external storage media and a random access memory computer. This threat is caused by vulnerabilities BIOS / UEFI software designed for testing and computer maintenance (funds check memory integrity, software RAID-controller management software, etc.). Realization of this threat may contribute to the ability to update some of the BIOS / UEFI without passing authentication | M14: =IFERROR(__xludf.DUMMYFUNCTION("GOOGLETRANSLATE(F15, ""auto"", ""en"")"),"Insider with a low potential") -> Insider with a low potential | N14: =IFERROR(__xludf.DUMMYFUNCTION("GOOGLETRANSLATE(H15, ""auto"", ""en"")"),"BIOS / UEFI firmware") -> BIOS / UEFI firmware
B15: בקרת גישה | C15: רשלנות מקצועית | D15: איום פנימי | E15: הצצה למחשבים/רשומות מסווגות | F15: גישה פיזית | G15: 3 | H15: 3 | J15: 14 | K15: =IFERROR(__xludf.DUMMYFUNCTION("GOOGLETRANSLATE(B16, ""auto"", ""en"")"),"The threat of long-term retention of the user's computing resources") -> The threat of long-term retention of the user's computing resources | L15: =IFERROR(__xludf.DUMMYFUNCTION("GOOGLETRANSLATE(D16, ""auto"", ""en"")"),"The threat is the possibility of limiting the infringer end-user access to computing resources at the expense of his forced confinement in a loaded state by repeatedly performing the exercise of certain destructive action or operation, distributing comput"&"ing resources among tasks for application vulnerabilities. This threat is caused by weaknesses load balancing and allocation of computing resources. Implementation of the threat is possible if the offender has the opportunity to make requests, all of wh"&"ich require more time to complete than the user requests") -> The threat is the possibility of limiting the infringer end-user access to computing resources at the expense of his forced confinement in a loaded state by repeatedly performing the exercise of certain destructive action or operation, distributing computing resources among tasks for application vulnerabilities. This threat is caused by weaknesses load balancing and allocation of computing resources. Implementation of the threat is possible if the offender has the opportunity to make requests, all of which require more time to complete than the user requests | M15: =IFERROR(__xludf.DUMMYFUNCTION("GOOGLETRANSLATE(F16, ""auto"", ""en"")"),"External intruder low potential insider with a low potential") -> External intruder low potential insider with a low potential | N15: =IFERROR(__xludf.DUMMYFUNCTION("GOOGLETRANSLATE(H16, ""auto"", ""en"")"),"Information System, a network node, data carrier, system software, network software, network traffic") -> Information System, a network node, data carrier, system software, network software, network traffic
B16: אבטחת רשת | C16: שיבוש/השבתת שירותים | D16: איום חיצוני | E16: מניעת גישה למידע ואו שירות באתר אינטרנט באמצעות השבתת הרכיב על ידי מתקפת DDOS | F16: גישה פיזית, גישה ידי | G16: 2 | H16: 3 | J16: 15 | K16: =IFERROR(__xludf.DUMMYFUNCTION("GOOGLETRANSLATE(B17, ""auto"", ""en"")"),"The threat of access to protected files using the workaround") -> The threat of access to protected files using the workaround | L16: =IFERROR(__xludf.DUMMYFUNCTION("GOOGLETRANSLATE(D17, ""auto"", ""en"")"),"The threat is the possibility of obtaining the offender access to the hidden / protected folders or files through various actions on the file system (to add additional characters to specify a file path, accessing files that are not explicitly listed in th"&"e application window). This threat is due to the weaknesses of the mechanism of differentiation of access to file system objects. Implementation of this threat is possible under the conditions: the presence of the violator of the rights of access to ce"&"rtain file system objects; lack of verification data entered by the user; possession diskreditiruemoy program too high privilege access to the files, the processing of which is not intended to help her") -> The threat is the possibility of obtaining the offender access to the hidden / protected folders or files through various actions on the file system (to add additional characters to specify a file path, accessing files that are not explicitly listed in the application window). This threat is due to the weaknesses of the mechanism of differentiation of access to file system objects. Implementation of this threat is possible under the conditions: the presence of the violator of the rights of access to certain file system objects; lack of verification data entered by the user; possession diskreditiruemoy program too high privilege access to the files, the processing of which is not intended to help her | M16: =IFERROR(__xludf.DUMMYFUNCTION("GOOGLETRANSLATE(F17, ""auto"", ""en"")"),"External intruder low potential insider with a low potential") -> External intruder low potential insider with a low potential | N16: =IFERROR(__xludf.DUMMYFUNCTION("GOOGLETRANSLATE(H17, ""auto"", ""en"")"),"File System Objects") -> File System Objects
B17: שרשרת אספקה ומיקור חוץ | C17: פרסום מידע סודי/שגוי | D17: איום פנימי | E17: הפצת מידע עסקי, פנימי ואו כוזב באתר אינטרנט (תכניות אסטרטגיות, סודות מסחריים, גורמים חיצוניים, לקוחות, שותפים עסקיים וכו') | F17: גישה פיזית, גישה שותפים | G17: 2 | H17: 1 | J17: 16 | K17: =IFERROR(__xludf.DUMMYFUNCTION("GOOGLETRANSLATE(B18, ""auto"", ""en"")"),"The threat of access to local files on the server using the URL") -> The threat of access to local files on the server using the URL | L17: =IFERROR(__xludf.DUMMYFUNCTION("GOOGLETRANSLATE(D18, ""auto"", ""en"")"),"The threat is the possibility of transfer of the offender diskreditiruemomu browser request for access to the file system user instead of URL-request. In this browser execute this request to the rights that he is endowed with at startup, and transmit data"&" obtained as a result of this operation, the violator. This threat is caused by weaknesses introduced by the user requests a verification mechanism, which does not distinguish between requests for access to the file system, and URL-requests. Implementat"&"ion of this threat is possible in the case of the offender privileges to send a browser request, the system operates in diskreditiruemoy") -> The threat is the possibility of transfer of the offender diskreditiruemomu browser request for access to the file system user instead of URL-request. In this browser execute this request to the rights that he is endowed with at startup, and transmit data obtained as a result of this operation, the violator. This threat is caused by weaknesses introduced by the user requests a verification mechanism, which does not distinguish between requests for access to the file system, and URL-requests. Implementation of this threat is possible in the case of the offender privileges to send a browser request, the system operates in diskreditiruemoy | M17: =IFERROR(__xludf.DUMMYFUNCTION("GOOGLETRANSLATE(F18, ""auto"", ""en"")"),"The outer middle potential violator") -> The outer middle potential violator | N17: =IFERROR(__xludf.DUMMYFUNCTION("GOOGLETRANSLATE(H18, ""auto"", ""en"")"),"Networking software") -> Networking software
B18: הגנה על המידע | C18: האזנה לסניף בחו"ל מול המטה בישראל | D18: איום חיצוני | E18: נגישות לנתונים של הארגון אשר עוברים בתווך בינ"ל מול המערכות בסניף בחו"ל. לדוגמא האזנה לתקשורת בין רכיבי מחשוב של מערכת שלא בדרך קונבנציונלית (לדוגמא באמצעות שדה מגנטי בכבלים) ואו נגישות לנתונים של הארגון אשר עוברים בתווך בינ"ל | F18: גישה פיזית, גישה בתווך | G18: 1 | H18: 1 | J18: 17 | K18: =IFERROR(__xludf.DUMMYFUNCTION("GOOGLETRANSLATE(B19, ""auto"", ""en"")"),"The threat of an access / interception / modification HTTP cookies") -> The threat of an access / interception / modification HTTP cookies | L18: =IFERROR(__xludf.DUMMYFUNCTION("GOOGLETRANSLATE(D19, ""auto"", ""en"")"),"The threat is the possibility of the perpetrator of unauthorized access to protected information (user accounts, certificates, etc.) contained in the cookies-files during storage or transmission, in read mode (the disclosure of privacy) or write (amendmen"&"ts to implementation of threat spoofing a trusted user). This threat is caused by weakness protection cookies-file action: the absence of verification of input data from a network service that uses cookies-files, as well as the lack of encryption when se"&"nding cookies-files. Implementation of this threat is possible under the conditions of a successful intruder unauthorized access to cookies-files and check the integrity of the absence of their values ​​from the application diskreditiruemogo") -> The threat is the possibility of the perpetrator of unauthorized access to protected information (user accounts, certificates, etc.) contained in the cookies-files during storage or transmission, in read mode (the disclosure of privacy) or write (amendments to implementation of threat spoofing a trusted user). This threat is caused by weakness protection cookies-file action: the absence of verification of input data from a network service that uses cookies-files, as well as the lack of encryption when sending cookies-files. Implementation of this threat is possible under the conditions of a successful intruder unauthorized access to cookies-files and check the integrity of the absence of their values ​​from the application diskreditiruemogo | M18: =IFERROR(__xludf.DUMMYFUNCTION("GOOGLETRANSLATE(F19, ""auto"", ""en"")"),"External intruder with a low potential") -> External intruder with a low potential | N18: =IFERROR(__xludf.DUMMYFUNCTION("GOOGLETRANSLATE(H19, ""auto"", ""en"")"),"Application software, network software") -> Application software, network software
B19: בקרת גישה | C19: שטח למטה (סקאדה) | D19: איום פנימי | E19: הרכשה ושימוש בערוץ התקשורת מול הציוד בשטח | F19: גישה פיזית, גישה מול | G19: 1 | H19: 1 | J19: 18 | K19: =IFERROR(__xludf.DUMMYFUNCTION("GOOGLETRANSLATE(B20, ""auto"", ""en"")"),"Download Threat abnormal operating system") -> Download Threat abnormal operating system | L19: =IFERROR(__xludf.DUMMYFUNCTION("GOOGLETRANSLATE(D20, ""auto"", ""en"")"),"The threat is the possibility of substitution of the violator a bootable operating system by unauthorized reconfiguration in the BIOS / UEFI access path to boot the operating system. This threat is caused by weaknesses technologies restricting access to "&"the BIOS / UEFI management. Implementation of this threat can be provided access to the offender the next parameter BIOS / UEFI settings - indication of the operating system boot source") -> The threat is the possibility of substitution of the violator a bootable operating system by unauthorized reconfiguration in the BIOS / UEFI access path to boot the operating system. This threat is caused by weaknesses technologies restricting access to the BIOS / UEFI management. Implementation of this threat can be provided access to the offender the next parameter BIOS / UEFI settings - indication of the operating system boot source | M19: =IFERROR(__xludf.DUMMYFUNCTION("GOOGLETRANSLATE(F20, ""auto"", ""en"")"),"Insider with a low potential") -> Insider with a low potential | N19: =IFERROR(__xludf.DUMMYFUNCTION("GOOGLETRANSLATE(H20, ""auto"", ""en"")"),"BIOS / UEFI firmware") -> BIOS / UEFI firmware
B20: מניעת קוד זדוני | C20: קשר של הארגון עם גורמים חיצוניים | D20: איום חיצוני/שרשרת אספקה | E20: הטמנת קוד עוין בקבצים המועברים מהחברה לארגון - דרך המחשב של החברה ואו באתר אחסון המסמכים | F20: גישה פיזית, גישה באתר | G20: 2 | H20: 2 | J20: 19 | K20: =IFERROR(__xludf.DUMMYFUNCTION("GOOGLETRANSLATE(B21, ""auto"", ""en"")"),"The threat of DNS-cache infection") -> The threat of DNS-cache infection | L20: =IFERROR(__xludf.DUMMYFUNCTION("GOOGLETRANSLATE(D21, ""auto"", ""en"")"),"The threat is the ability to redirect network traffic violator through its own network node mediated by changes in the relevant tables IP- and domain names that are stored in the DNS-server, at the expense of generating an avalanche of possible responses "&"to the request DNS-server a valid user, or by exploiting the DNS-server vulnerabilities . This threat is caused by weakness of mechanisms authentication networking subjects, as well as DNS-server vulnerabilities that can directly replace the DNS-cache DN"&"S-server. Implementation of this threat is possible in the case of the offender privileges sufficient to send network requests to the DNS-server") -> The threat is the ability to redirect network traffic violator through its own network node mediated by changes in the relevant tables IP- and domain names that are stored in the DNS-server, at the expense of generating an avalanche of possible responses to the request DNS-server a valid user, or by exploiting the DNS-server vulnerabilities . This threat is caused by weakness of mechanisms authentication networking subjects, as well as DNS-server vulnerabilities that can directly replace the DNS-cache DNS-server. Implementation of this threat is possible in the case of the offender privileges sufficient to send network requests to the DNS-server | M20: =IFERROR(__xludf.DUMMYFUNCTION("GOOGLETRANSLATE(F21, ""auto"", ""en"")"),"External intruder with a low potential") -> External intruder with a low potential | N20: =IFERROR(__xludf.DUMMYFUNCTION("GOOGLETRANSLATE(H21, ""auto"", ""en"")"),"Network node, network software, network traffic") -> Network node, network software, network traffic
B21: בקרת גישה | C21: ניצול הרשאות עובד פנימי/חיצוני | D21: איום פנימי/חיצוני | E21: גיוס/ניצול בעל תפקיד עם הרשאות גבוהות, יכולת השפעה על המערכות/תהליכים, גישה מורשית רחבה למידע ואו נגישות פיזית למתחמים מסווגים והשבתתן/שיבושן תוך ביצוע נזק פיזי/לוגי ופרסום הנזק | F21: גישת הרשאות, גישה רשתית | G21: 1 | H21: 2 | J21: 20 | K21: =IFERROR(__xludf.DUMMYFUNCTION("GOOGLETRANSLATE(B22, ""auto"", ""en"")"),"The threat of abuse the opportunities offered by cloud-based services to consumers") -> The threat of abuse the opportunities offered by cloud-based services to consumers | L21: =IFERROR(__xludf.DUMMYFUNCTION("GOOGLETRANSLATE(D22, ""auto"", ""en"")"),"The threat is the possibility of the consumer of cloud services (the offender) spam, unauthorized access to the virtual machines to other consumers of cloud services or other destructive software effects on different systems using leased resources of the "&"cloud server. This threat stems from the fact that the cloud service consumer can install their own software on the cloud server. Implementation of this threat is possible by installing and running the consumer cloud services malicious software on the c"&"loud server. Successful implementation of this threat the consumer of cloud services has a negative effect on the reputation of the supplier of cloud services") -> The threat is the possibility of the consumer of cloud services (the offender) spam, unauthorized access to the virtual machines to other consumers of cloud services or other destructive software effects on different systems using leased resources of the cloud server. This threat stems from the fact that the cloud service consumer can install their own software on the cloud server. Implementation of this threat is possible by installing and running the consumer cloud services malicious software on the cloud server. Successful implementation of this threat the consumer of cloud services has a negative effect on the reputation of the supplier of cloud services | M21: =IFERROR(__xludf.DUMMYFUNCTION("GOOGLETRANSLATE(F22, ""auto"", ""en"")"),"Insider with a low potential") -> Insider with a low potential | N21: =IFERROR(__xludf.DUMMYFUNCTION("GOOGLETRANSLATE(H22, ""auto"", ""en"")"),"Cloud system, the virtual machine") -> Cloud system, the virtual machine
B22: בקרת גישה | C22: ניצול הרשאות עובד פנימי/חיצוני | D22: איום פנימי/חיצוני | E22: גיוס/ניצול בעל תפקיד עם הרשאות משתמש וניסיון לבצע העלאת הרשאות, החדרת כלי תקיפה ע"י התוקף במחשב של המשתמש (ביקורת, ספק, עובד חיצוני וכדומה) והמחובר למערכות הארגון | F22: גישת הרשאות, גישה רשתית | G22: 2 | H22: 3 | J22: 21 | K22: =IFERROR(__xludf.DUMMYFUNCTION("GOOGLETRANSLATE(B23, ""auto"", ""en"")"),"The threat of abuse of trust cloud services consumers") -> The threat of abuse of trust cloud services consumers | L22: =IFERROR(__xludf.DUMMYFUNCTION("GOOGLETRANSLATE(D23, ""auto"", ""en"")"),"The threat is the possibility of a violation (accidentally or intentionally) security of information consumers of cloud services insiders provider of cloud services. This threat stems from the fact that a significant part of the security functions transf"&"erred to the responsibility of the provider of cloud services, as well as the impossibility of acceptance by the consumer of cloud services protection against the actions of the provider of cloud services. Implementation of this threat is possible provid"&"ed that consumers of cloud services is not part of the organization engaged in the provision of these cloud-based services (ie the consumer actually transferred to the supplier's own information for its processing)") -> The threat is the possibility of a violation (accidentally or intentionally) security of information consumers of cloud services insiders provider of cloud services. This threat stems from the fact that a significant part of the security functions transferred to the responsibility of the provider of cloud services, as well as the impossibility of acceptance by the consumer of cloud services protection against the actions of the provider of cloud services. Implementation of this threat is possible provided that consumers of cloud services is not part of the organization engaged in the provision of these cloud-based services (ie the consumer actually transferred to the supplier's own information for its processing) | M22: =IFERROR(__xludf.DUMMYFUNCTION("GOOGLETRANSLATE(F23, ""auto"", ""en"")"),"External intruder with a low potential") -> External intruder with a low potential | N22: =IFERROR(__xludf.DUMMYFUNCTION("GOOGLETRANSLATE(H23, ""auto"", ""en"")"),"cloud system") -> cloud system
B23: בקרת גישה | C23: ניצול הרשאות עובד פנימי/חיצוני | D23: איום פנימי/חיצוני | E23: גיוס/ניצול בעל תפקיד עם הרשאות משתמש ושימוש בחשבון של המשתמש כדי ליצור חשבונות נוספים ולהשתמש בחשבונות הללו לצורכי תקיפה תוך טשטוש יכולת הזיהוי של המתקפה בזמן אמת ואו באמצעות נתיב הביקורת | F23: גישת הרשאות, גישה רשתית | G23: 1 | H23: 2 | J23: 22 | K23: =IFERROR(__xludf.DUMMYFUNCTION("GOOGLETRANSLATE(B24, ""auto"", ""en"")"),"The threat of excess allocation of RAM") -> The threat of excess allocation of RAM | L23: =IFERROR(__xludf.DUMMYFUNCTION("GOOGLETRANSLATE(D24, ""auto"", ""en"")"),"The threat is the possibility of substantial resources of RAM to serve the malware requests and a corresponding decrease in the volume of RAM resources available in the system for allocation in response to legitimate users Program requests. This threat i"&"s caused by the presence of the weaknesses of the control mechanism for the allocation of memory to different programs. Implementation of this threat can be subject to a finding of malicious software in the active system") -> The threat is the possibility of substantial resources of RAM to serve the malware requests and a corresponding decrease in the volume of RAM resources available in the system for allocation in response to legitimate users Program requests. This threat is caused by the presence of the weaknesses of the control mechanism for the allocation of memory to different programs. Implementation of this threat can be subject to a finding of malicious software in the active system | M23: =IFERROR(__xludf.DUMMYFUNCTION("GOOGLETRANSLATE(F24, ""auto"", ""en"")"),"External intruder low potential insider with a low potential") -> External intruder low potential insider with a low potential | N23: =IFERROR(__xludf.DUMMYFUNCTION("GOOGLETRANSLATE(H24, ""auto"", ""en"")"),"Hardware, system software, network software") -> Hardware, system software, network software
B24: מניעת קוד זדוני | C24: הנדסה חברתית לעובד פנימי/חיצוני | D24: איום פנימי/חיצוני | E24: הדבקת מחשב של עובד באמצעים גלישה, לדוגמא: א. קוד עוין ברשת אשר יורד ישירות מהאתר ב. החדרת קוד עוין על גבי תעבורת הגלישה ג. החדרת קוד עוין על גבי תשתית החזרת נתוני שאילתה אפליקטיבית ד. חדירה באמצעות קוד עוין המקושר אל הרשת החברתית והדבקת התחנה כאשר מתבצעת פניה מתחנת העבודה לקישור | F24: גישה פיזית, גישה רשתית, גישה מרחוק | G24: 3 | H24: 3 | J24: 23 | K24: =IFERROR(__xludf.DUMMYFUNCTION("GOOGLETRANSLATE(B25, ""auto"", ""en"")"),"Threat of change components of information (automated) systems") -> Threat of change components of information (automated) systems | L24: =IFERROR(__xludf.DUMMYFUNCTION("GOOGLETRANSLATE(D25, ""auto"", ""en"")"),"The threat is the possibility of obtaining the offender access to network files, bookmarks and so on implementation by changing the composition unauthorized software or hardware information system, that further allow to carry out this intruder (or another"&" - external, to detect unauthorized access to the system channel) unauthorized actions in the system. This threat is due to the weaknesses of controls over the integrity of the hardware configuration of the information system. Implementation of this thr"&"eat can be subject to the successful receipt of the infringer necessary powers in the system and the possibility of connection of additional peripheral equipment") -> The threat is the possibility of obtaining the offender access to network files, bookmarks and so on implementation by changing the composition unauthorized software or hardware information system, that further allow to carry out this intruder (or another - external, to detect unauthorized access to the system channel) unauthorized actions in the system. This threat is due to the weaknesses of controls over the integrity of the hardware configuration of the information system. Implementation of this threat can be subject to the successful receipt of the infringer necessary powers in the system and the possibility of connection of additional peripheral equipment | M24: =IFERROR(__xludf.DUMMYFUNCTION("GOOGLETRANSLATE(F25, ""auto"", ""en"")"),"Insider with a low potential") -> Insider with a low potential | N24: =IFERROR(__xludf.DUMMYFUNCTION("GOOGLETRANSLATE(H25, ""auto"", ""en"")"),"Information system, server, workstation, virtual machine, system software, application software, hardware,") -> Information system, server, workstation, virtual machine, system software, application software, hardware,
B25: הדרכות | C25: הנדסה חברתית לעובד פנימי/חיצוני | D25: איום חיצוני | E25: הדבקת מחשב של עובד באמצעות מייל, לדוגמא: א. החדרת קוד עוין באמצעות שליחת קוד עוין המצורף להודעה. ב. הכנסת קישור (LINK) נגוע להודעה המפנה לאתר מתחזה והטעיית המשתמש | F25: גישה פיזית, גישה מתחזה | G25: 3 | H25: 3 | J25: 24 | K25: =IFERROR(__xludf.DUMMYFUNCTION("GOOGLETRANSLATE(B26, ""auto"", ""en"")"),"The threat of changing the mode of the computer hardware elements") -> The threat of changing the mode of the computer hardware elements | L25: =IFERROR(__xludf.DUMMYFUNCTION("GOOGLETRANSLATE(D26, ""auto"", ""en"")"),"The threat is the possibility of changing offender modes of hardware elements by computer BIOS / UEFI unauthorized reconfiguration that allows you to: by changing the frequency of the system bus data transmission mode of communication channels, etc. affe"&"ct the overall performance of your computer or cause malfunctions; due to the lowering of the input voltage, shutdown cooling system temporarily inoperable secure computer; due to the reference invalid operation device parameters (threshold device off w"&"hen overheated, input voltage, etc.) lead to a physical failure of individual computer hardware elements. This threat is caused by weaknesses technologies restricting access to the BIOS / UEFI management. Implementation of this threat can be provided th"&"at the offender privileges to change the corresponding parameters BIOS / UEFI settings") -> The threat is the possibility of changing offender modes of hardware elements by computer BIOS / UEFI unauthorized reconfiguration that allows you to: by changing the frequency of the system bus data transmission mode of communication channels, etc. affect the overall performance of your computer or cause malfunctions; due to the lowering of the input voltage, shutdown cooling system temporarily inoperable secure computer; due to the reference invalid operation device parameters (threshold device off when overheated, input voltage, etc.) lead to a physical failure of individual computer hardware elements. This threat is caused by weaknesses technologies restricting access to the BIOS / UEFI management. Implementation of this threat can be provided that the offender privileges to change the corresponding parameters BIOS / UEFI settings | M25: =IFERROR(__xludf.DUMMYFUNCTION("GOOGLETRANSLATE(F26, ""auto"", ""en"")"),"Insider with high potential") -> Insider with high potential | N25: =IFERROR(__xludf.DUMMYFUNCTION("GOOGLETRANSLATE(H26, ""auto"", ""en"")"),"Firmware and BIOS / UEFI hardware") -> Firmware and BIOS / UEFI hardware
B26: הגנת תחנות עבודה ושרתים | C26: הנדסה חברתית לעובד פנימי/חיצוני | D26: איום חיצוני | E26: הדבקת מחשב של עובד על ידי חיבור מדיה נתיקה נגועה בקוד עוין | F26: גישה פיזית, גישה נגועה | G26: 3 | H26: 3 | J26: 25 | K26: =IFERROR(__xludf.DUMMYFUNCTION("GOOGLETRANSLATE(B27, ""auto"", ""en"")"),"The threat of systemic change and global variables") -> The threat of systemic change and global variables | L26: =IFERROR(__xludf.DUMMYFUNCTION("GOOGLETRANSLATE(D27, ""auto"", ""en"")"),"The threat is the possibility of the offender mediated destructive effects on some software program or the entire system by changing the software used diskreditiruemymi unified system and global variables. This threat is caused by weaknesses in access co"&"ntrol mechanism for shared memory, and the vulnerabilities of software application modules that implement the external integrity of the control variables. Implementation of this threat is possible under the conditions of the intruder successfully unautho"&"rized access to the system and global variables and their lack of integrity checking values ​​from the application diskreditiruemogo") -> The threat is the possibility of the offender mediated destructive effects on some software program or the entire system by changing the software used diskreditiruemymi unified system and global variables. This threat is caused by weaknesses in access control mechanism for shared memory, and the vulnerabilities of software application modules that implement the external integrity of the control variables. Implementation of this threat is possible under the conditions of the intruder successfully unauthorized access to the system and global variables and their lack of integrity checking values ​​from the application diskreditiruemogo | M26: =IFERROR(__xludf.DUMMYFUNCTION("GOOGLETRANSLATE(F27, ""auto"", ""en"")"),"The inner middle potential violator") -> The inner middle potential violator | N26: =IFERROR(__xludf.DUMMYFUNCTION("GOOGLETRANSLATE(H27, ""auto"", ""en"")"),"System software, application software, networking software") -> System software, application software, networking software
B27: הדרכות | C27: הנדסה חברתית לעובד פנימי/חיצוני | D27: איום פנימי | E27: מסירת מידע ערכי ואו מסווג לגורמים לא מורשים ואו לתוקף, באופן וורבלי ואו באמצעות ניירת פיזית, העלולים לשמש לתקיפת המערכת | F27: גישה פיזית, גישה לשמש | G27: 3 | H27: 3 | J27: 26 | K27: =IFERROR(__xludf.DUMMYFUNCTION("GOOGLETRANSLATE(B28, ""auto"", ""en"")"),"The threat of distortion of XML-schema") -> The threat of distortion of XML-schema | L27: =IFERROR(__xludf.DUMMYFUNCTION("GOOGLETRANSLATE(D28, ""auto"", ""en"")"),"The threat lies in the possibility of changing the violator information processing algorithm applications functioning on the basis of XML-schema, until the application driving condition ""Denial of Service"", by changing the XML-schema exchanged between t"&"he client and server. This threat is caused by weakness of measures to ensure the integrity of transmitted when the client-server interaction data, as well as the weaknesses of the mechanism of interaction of open systems network. Implementation of this"&" threat is possible under the conditions of a successful intruder unauthorized access to the network traffic between the client and the server and there is no integrity checking XML-schema from diskreditiruemogo applications") -> The threat lies in the possibility of changing the violator information processing algorithm applications functioning on the basis of XML-schema, until the application driving condition "Denial of Service", by changing the XML-schema exchanged between the client and server. This threat is caused by weakness of measures to ensure the integrity of transmitted when the client-server interaction data, as well as the weaknesses of the mechanism of interaction of open systems network. Implementation of this threat is possible under the conditions of a successful intruder unauthorized access to the network traffic between the client and the server and there is no integrity checking XML-schema from diskreditiruemogo applications | M27: =IFERROR(__xludf.DUMMYFUNCTION("GOOGLETRANSLATE(F28, ""auto"", ""en"")"),"External intruder with an average potential intruder inner middle potential") -> External intruder with an average potential intruder inner middle potential | N27: =IFERROR(__xludf.DUMMYFUNCTION("GOOGLETRANSLATE(H28, ""auto"", ""en"")"),"Network node, network software, network traffic") -> Network node, network software, network traffic
B28: הפרדת סביבות | C28: רשלנות מקצועית | D28: איום פנימי | E28: יצירת קישור לא מאובטח בין רשתות מבודלות | F28: גישה פיזית, גישה בין | G28: 3 | H28: 3 | J28: 27 | K28: =IFERROR(__xludf.DUMMYFUNCTION("GOOGLETRANSLATE(B29, ""auto"", ""en"")"),"The threat of distortion on input and output peripherals information") -> The threat of distortion on input and output peripherals information | L28: =IFERROR(__xludf.DUMMYFUNCTION("GOOGLETRANSLATE(D29, ""auto"", ""en"")"),"The threat lies in the possibility of disinformation user or automatic control systems by spoofing or tampering raw data received from sensors, keyboards or other input devices, as well as substitution or tampering information displayed on the printer ope"&"rator display or other peripheral devices. This threat is due to weaknesses measures antivirus protection and reliability of the control of input and output data, and errors made during the inspection of special hardware computing. Implementation of thi"&"s threat can be subject to availability of an information system in diskreditiruemoy malicious software (e.g., virtual device drivers) or hardware bookmarking") -> The threat lies in the possibility of disinformation user or automatic control systems by spoofing or tampering raw data received from sensors, keyboards or other input devices, as well as substitution or tampering information displayed on the printer operator display or other peripheral devices. This threat is due to weaknesses measures antivirus protection and reliability of the control of input and output data, and errors made during the inspection of special hardware computing. Implementation of this threat can be subject to availability of an information system in diskreditiruemoy malicious software (e.g., virtual device drivers) or hardware bookmarking | M28: =IFERROR(__xludf.DUMMYFUNCTION("GOOGLETRANSLATE(F29, ""auto"", ""en"")"),"External attackers with a high potential insider with a low potential") -> External attackers with a high potential insider with a low potential | N28: =IFERROR(__xludf.DUMMYFUNCTION("GOOGLETRANSLATE(H29, ""auto"", ""en"")"),"System software, application software, network software, hardware") -> System software, application software, network software, hardware
B29: סקרי הערכת בקרות אבטחה | C29: רשלנות מקצועית | D29: איום הפנימי | E29: קנפוג/הקשחה לא מספקת/לא נכונה של אמצעי אבטחה ומחשוב | G29: 3 | H29: 3 | J29: 28 | K29: =IFERROR(__xludf.DUMMYFUNCTION("GOOGLETRANSLATE(B30, ""auto"", ""en"")"),"The threat of the use of alternative routes of access to resources") -> The threat of the use of alternative routes of access to resources | L29: =IFERROR(__xludf.DUMMYFUNCTION("GOOGLETRANSLATE(D30, ""auto"", ""en"")"),"The threat is the possibility of wrongdoing unauthorized access to protected information bypassing regular arrangements using non-standard interfaces (including access from a command line bypassing GUI). This threat is caused by weakness of measures rest"&"ricting access to protected information, weaknesses input filtering. Implementation of this threat can be provided that the offender: ability to input arbitrary data into the address bar; information about the path to a protected resource; possibility"&" of changing the input interface input") -> The threat is the possibility of wrongdoing unauthorized access to protected information bypassing regular arrangements using non-standard interfaces (including access from a command line bypassing GUI). This threat is caused by weakness of measures restricting access to protected information, weaknesses input filtering. Implementation of this threat can be provided that the offender: ability to input arbitrary data into the address bar; information about the path to a protected resource; possibility of changing the input interface input | M29: =IFERROR(__xludf.DUMMYFUNCTION("GOOGLETRANSLATE(F30, ""auto"", ""en"")"),"External intruder low potential insider with a low potential") -> External intruder low potential insider with a low potential | N29: =IFERROR(__xludf.DUMMYFUNCTION("GOOGLETRANSLATE(H30, ""auto"", ""en"")"),"Network node's file system, application software, system software") -> Network node's file system, application software, system software
B30: ניהול אירועים ודיווח | C30: עובד ממורמר | D30: איום הפנימי | E30: שימוש בהרשאותיו הלגיטימיות לפעולות לא מורשות/גישה למידע שאינו מיועד עבורו | F30: גישה ממורמר, גישה רשתית | G30: 2 | H30: 3 | J30: 29 | K30: =IFERROR(__xludf.DUMMYFUNCTION("GOOGLETRANSLATE(B31, ""auto"", ""en"")"),"The threat of the use of the computing resources of a supercomputer ""parasitic"" processes") -> The threat of the use of the computing resources of a supercomputer "parasitic" processes | L30: =IFERROR(__xludf.DUMMYFUNCTION("GOOGLETRANSLATE(D31, ""auto"", ""en"")"),"The threat is the possibility of a significant reduction in performance computing field supercomputer and the effectiveness of the current on it parallel computing because computing resources consumption supercomputer ""parasitic"" process ( ""child proce"&"sses"" of the previous tasks or processes running malicious software). This threat is caused by weakness of memory cleaning measures from the ""child process"" of completed tasks and processes running malicious software. Implementation of this threat ca"&"n be provided incorrect completion of tasks or processes in the presence of malicious memory supercomputer active") -> The threat is the possibility of a significant reduction in performance computing field supercomputer and the effectiveness of the current on it parallel computing because computing resources consumption supercomputer "parasitic" process ( "child processes" of the previous tasks or processes running malicious software). This threat is caused by weakness of memory cleaning measures from the "child process" of completed tasks and processes running malicious software. Implementation of this threat can be provided incorrect completion of tasks or processes in the presence of malicious memory supercomputer active | M30: =IFERROR(__xludf.DUMMYFUNCTION("GOOGLETRANSLATE(F31, ""auto"", ""en"")"),"External intruder low potential insider with a low potential") -> External intruder low potential insider with a low potential | N30: =IFERROR(__xludf.DUMMYFUNCTION("GOOGLETRANSLATE(H31, ""auto"", ""en"")"),"Compute nodes supercomputer") -> Compute nodes supercomputer
B31: שרשרת אספקה ומיקור חוץ | C31: מתקני אירוח חיצוניים HOSTING (שלא בניהול הארגון) | D31: איום חיצוני | E31: חדירה לתווך/ציוד תקשורת/מערכות/מחשבי קצה של הספק אשר מחוברות למערכות הארגון. | F31: גישה אירוח, גישה רשתית | G31: 2 | H31: 2 | J31: 30 | K31: =IFERROR(__xludf.DUMMYFUNCTION("GOOGLETRANSLATE(B32, ""auto"", ""en"")"),"the use of information threat identification / authentication, the default") -> the use of information threat identification / authentication, the default | L31: =IFERROR(__xludf.DUMMYFUNCTION("GOOGLETRANSLATE(D32, ""auto"", ""en"")"),"The threat is the possibility of passing the intruder authorization procedure based on information from open sources of identity and authentication information corresponding to the ""default"" account diskreditiruemogo object of protection. This threat i"&"s due to the fact that in the ""default"" set of software and software-hardware manufacturers provided accounts, intended for primary logon. Moreover, in many devices the identification and authentication information may be returned to the predetermined "&"""default"" after a hard reset of the system parameters (Reset function). Implementation of this threat is possible if one of the following conditions: the presence of the intruder information about the manufacturer / model of the object of protection a"&"nd the availability of open sources of information about the identification and authentication information corresponding to the account ""default"" for the protection of the object; successful completion of the procedures to identify the infringer of the"&" information in the software code analysis diskreditiruemogo object protection") -> The threat is the possibility of passing the intruder authorization procedure based on information from open sources of identity and authentication information corresponding to the "default" account diskreditiruemogo object of protection. This threat is due to the fact that in the "default" set of software and software-hardware manufacturers provided accounts, intended for primary logon. Moreover, in many devices the identification and authentication information may be returned to the predetermined "default" after a hard reset of the system parameters (Reset function). Implementation of this threat is possible if one of the following conditions: the presence of the intruder information about the manufacturer / model of the object of protection and the availability of open sources of information about the identification and authentication information corresponding to the account "default" for the protection of the object; successful completion of the procedures to identify the infringer of the information in the software code analysis diskreditiruemogo object protection | M31: =IFERROR(__xludf.DUMMYFUNCTION("GOOGLETRANSLATE(F32, ""auto"", ""en"")"),"External intruder with an average potential insider with a low potential") -> External intruder with an average potential insider with a low potential | N31: =IFERROR(__xludf.DUMMYFUNCTION("GOOGLETRANSLATE(H32, ""auto"", ""en"")"),"Information security tools, system software, network software, firmware, software and hardware with built-in security features") -> Information security tools, system software, network software, firmware, software and hardware with built-in security features
B32: שרשרת אספקה ומיקור חוץ | C32: מתקני אירוח חיצוניים HOSTING (שלא בניהול הארגון) | D32: איום חיצוני/שרשרת אספקה | E32: חדירה למערכות הארגון דרך מערכות של לקוח אחר שמתארח במתקן | F32: גישה פיזית, גישה אחר | G32: 2 | H32: 2 | J32: 31 | K32: =IFERROR(__xludf.DUMMYFUNCTION("GOOGLETRANSLATE(B33, ""auto"", ""en"")"),"The threat of the use of the authorization mechanisms for elevation of privilege") -> The threat of the use of the authorization mechanisms for elevation of privilege | L32: =IFERROR(__xludf.DUMMYFUNCTION("GOOGLETRANSLATE(D33, ""auto"", ""en"")"),"The threat is the possibility of obtaining the offender access to the data and functions designed to accounts with higher than the offender privileges due to errors in the parameters means setting access control. In this case the offender to increase thei"&"r privileges does not carry a destructive impact on the system software, but only uses the existing errors. This threat is caused by weakness of measures restricting access to programs and files. Implementation of this threat is possible in the case of "&"the offender to any privileges in the system") -> The threat is the possibility of obtaining the offender access to the data and functions designed to accounts with higher than the offender privileges due to errors in the parameters means setting access control. In this case the offender to increase their privileges does not carry a destructive impact on the system software, but only uses the existing errors. This threat is caused by weakness of measures restricting access to programs and files. Implementation of this threat is possible in the case of the offender to any privileges in the system | M32: =IFERROR(__xludf.DUMMYFUNCTION("GOOGLETRANSLATE(F33, ""auto"", ""en"")"),"External intruder low potential insider with a low potential") -> External intruder low potential insider with a low potential | N32: =IFERROR(__xludf.DUMMYFUNCTION("GOOGLETRANSLATE(H33, ""auto"", ""en"")"),"System software, application software, networking software") -> System software, application software, networking software
B33: בקרת גישה | C33: האזנה מרחוק | D33: איום חיצוני | E33: הפעלה מרחוק של המיקרופון/מצלמה במחשב אינטרנט | G33: 2 | H33: 3 | J33: 32 | K33: =IFERROR(__xludf.DUMMYFUNCTION("GOOGLETRANSLATE(B34, ""auto"", ""en"")"),"The threat of the use of forged signatures BIOS") -> The threat of the use of forged signatures BIOS | L33: =IFERROR(__xludf.DUMMYFUNCTION("GOOGLETRANSLATE(D34, ""auto"", ""en"")"),"The threat is the possibility of installing a vulnerable version of the update BIOS / UEFI version or containing malware, but with a digital signature. This threat is caused by weakness of measures to control the trustworthiness centers issuing digital s"&"ignatures. Implementation of this threat can be subject to the issuance of unreliable CA digital signature version of BIOS / UEFI updates containing the vulnerabilities or version that contains malicious software (ie, the implementation of such a center "&"for fraud), as well as the substitution of the violator a trusted source of updates") -> The threat is the possibility of installing a vulnerable version of the update BIOS / UEFI version or containing malware, but with a digital signature. This threat is caused by weakness of measures to control the trustworthiness centers issuing digital signatures. Implementation of this threat can be subject to the issuance of unreliable CA digital signature version of BIOS / UEFI updates containing the vulnerabilities or version that contains malicious software (ie, the implementation of such a center for fraud), as well as the substitution of the violator a trusted source of updates | M33: =IFERROR(__xludf.DUMMYFUNCTION("GOOGLETRANSLATE(F34, ""auto"", ""en"")"),"The outer middle potential violator") -> The outer middle potential violator | N33: =IFERROR(__xludf.DUMMYFUNCTION("GOOGLETRANSLATE(H34, ""auto"", ""en"")"),"Firmware and BIOS / UEFI hardware") -> Firmware and BIOS / UEFI hardware
B34: בקרת גישה | C34: האזנה מרחוק | D34: איום חיצוני | E34: הפעלה מרחוק של המיקרופון בטלפון IP | F34: גישה המיקרופון | G34: 3 | H34: 1 | J34: 33 | K34: =IFERROR(__xludf.DUMMYFUNCTION("GOOGLETRANSLATE(B35, ""auto"", ""en"")"),"Use threat weaknesses coding input") -> Use threat weaknesses coding input | L34: =IFERROR(__xludf.DUMMYFUNCTION("GOOGLETRANSLATE(D35, ""auto"", ""en"")"),"The threat is the possibility of wrongdoing on the information impact destructive diskreditiruemuyu system by manipulating the values ​​of the input data and the form of their (alternative encodings incorrect file extension, etc.). This threat is due to "&"the weaknesses of the mechanism of input control. Implementation of this threat is possible under the conditions: diskreditiruemaya system accepts input data from the intruder; intruder has the ability to control one or more parameters of the input dat"&"a") -> The threat is the possibility of wrongdoing on the information impact destructive diskreditiruemuyu system by manipulating the values ​​of the input data and the form of their (alternative encodings incorrect file extension, etc.). This threat is due to the weaknesses of the mechanism of input control. Implementation of this threat is possible under the conditions: diskreditiruemaya system accepts input data from the intruder; intruder has the ability to control one or more parameters of the input data | M34: =IFERROR(__xludf.DUMMYFUNCTION("GOOGLETRANSLATE(F35, ""auto"", ""en"")"),"External intruder with an average potential intruder inner middle potential") -> External intruder with an average potential intruder inner middle potential | N34: =IFERROR(__xludf.DUMMYFUNCTION("GOOGLETRANSLATE(H35, ""auto"", ""en"")"),"System software, application software, network software, firmware, registry") -> System software, application software, network software, firmware, registry
B35: בקרת גישה | C35: האזנה מרחוק | D35: איום חיצוני | E35: הפעלה מרחוק של המיקרופון בטלפון נייד | F35: גישה המיקרופון | G35: 3 | H35: 2 | J35: 34 | K35: =IFERROR(__xludf.DUMMYFUNCTION("GOOGLETRANSLATE(B36, ""auto"", ""en"")"),"The threat of the use of the weaknesses of the protocols of network / local data exchange") -> The threat of the use of the weaknesses of the protocols of network / local data exchange | L35: =IFERROR(__xludf.DUMMYFUNCTION("GOOGLETRANSLATE(D36, ""auto"", ""en"")"),"The threat is the possibility of the perpetrator of unauthorized access to protected information transmitted in the system due to the destructive impact on the protocols of network / local communication system by breaking the rules of these protocols use."&" This threat is caused by weakness of protocols themselves (their inherent algorithms), errors made in the implementation of the protocols, or vulnerabilities being introduced computer-aided design / development tools. Implementation of this threat is p"&"ossible in case of weaknesses in the protocols of network / local data exchange") -> The threat is the possibility of the perpetrator of unauthorized access to protected information transmitted in the system due to the destructive impact on the protocols of network / local communication system by breaking the rules of these protocols use. This threat is caused by weakness of protocols themselves (their inherent algorithms), errors made in the implementation of the protocols, or vulnerabilities being introduced computer-aided design / development tools. Implementation of this threat is possible in case of weaknesses in the protocols of network / local data exchange | M35: =IFERROR(__xludf.DUMMYFUNCTION("GOOGLETRANSLATE(F36, ""auto"", ""en"")"),"External intruder low potential insider with a low potential") -> External intruder low potential insider with a low potential | N35: =IFERROR(__xludf.DUMMYFUNCTION("GOOGLETRANSLATE(H36, ""auto"", ""en"")"),"System software, network software, network traffic") -> System software, network software, network traffic
B36: הפרדת סביבות | C36: חדירה מהאינטרנט ישירות לרשת הארגון | D36: איום חיצוני | E36: דילוג מרכיב לרכיב (שרתים, תקשורת, מערכות) באמצעות ניצול הקישור ביניהם | F36: גישה פיזית, גישה ניצול | G36: 2 | H36: 2 | J36: 35 | K36: =IFERROR(__xludf.DUMMYFUNCTION("GOOGLETRANSLATE(B37, ""auto"", ""en"")"),"Threat to use weak cryptography algorithms BIOS") -> Threat to use weak cryptography algorithms BIOS | L36: =IFERROR(__xludf.DUMMYFUNCTION("GOOGLETRANSLATE(D37, ""auto"", ""en"")"),"The threat lies in the complexity of testing the actual operating parameters and algorithms implemented in cryptographic BIOS / UEFI tools. In this case, the credibility of the cryptographic protection is limited confidence in the BIOS manufacturer. This"&" threat is due to the complexity of using its own cryptographic algorithms in BIOS / UEFI software. The possibility of realization of the threat reduces the accuracy of the assessment of the actual level of security of the system") -> The threat lies in the complexity of testing the actual operating parameters and algorithms implemented in cryptographic BIOS / UEFI tools. In this case, the credibility of the cryptographic protection is limited confidence in the BIOS manufacturer. This threat is due to the complexity of using its own cryptographic algorithms in BIOS / UEFI software. The possibility of realization of the threat reduces the accuracy of the assessment of the actual level of security of the system | M36: =IFERROR(__xludf.DUMMYFUNCTION("GOOGLETRANSLATE(F37, ""auto"", ""en"")"),"External intruder with a high potential") -> External intruder with a high potential | N36: =IFERROR(__xludf.DUMMYFUNCTION("GOOGLETRANSLATE(H37, ""auto"", ""en"")"),"BIOS / UEFI firmware") -> BIOS / UEFI firmware
B37: הפרדת סביבות | C37: חדירה מהאינטרנט ישירות לרשת הארגון | D37: איום חיצוני | E37: חדירה לרשת ה- VOIP וממנה דילוג לרשתות אחרות | F37: גישה פיזית, גישה דילוג | G37: 2 | H37: 1 | J37: 36 | K37: =IFERROR(__xludf.DUMMYFUNCTION("GOOGLETRANSLATE(B38, ""auto"", ""en"")"),"The threat of the research program of the mechanisms") -> The threat of the research program of the mechanisms | L37: =IFERROR(__xludf.DUMMYFUNCTION("GOOGLETRANSLATE(D38, ""auto"", ""en"")"),"The threat is the possibility of the offender reverse engineering of program code and further study of its structure, functionality and structure of the benefit determination algorithm of the program and find vulnerabilities in it. This threat is due to "&"the weaknesses of the mechanism of protection of program code from the study. Implementation of this threat is possible in the following cases: the presence of the offender access to the source files of the program; the presence of the offender access "&"to the installation program and the lack of mechanism to protect the program code of the research") -> The threat is the possibility of the offender reverse engineering of program code and further study of its structure, functionality and structure of the benefit determination algorithm of the program and find vulnerabilities in it. This threat is due to the weaknesses of the mechanism of protection of program code from the study. Implementation of this threat is possible in the following cases: the presence of the offender access to the source files of the program; the presence of the offender access to the installation program and the lack of mechanism to protect the program code of the research | M37: =IFERROR(__xludf.DUMMYFUNCTION("GOOGLETRANSLATE(F38, ""auto"", ""en"")"),"External intruder with an average potential intruder inner middle potential") -> External intruder with an average potential intruder inner middle potential | N37: =IFERROR(__xludf.DUMMYFUNCTION("GOOGLETRANSLATE(H38, ""auto"", ""en"")"),"System software, application software, network software, firmware") -> System software, application software, network software, firmware
B38: אבטחת רשת | C38: חדירה מהאינטרנט ישירות לרשת הארגון | D38: איום פנימי/חיצוני | E38: מיפוי משתמשי הארגון, חשבונות, כתובות, מבנה ארגוני ועוד | F38: גישה פיזית, גישה מבנה | G38: 3 | H38: 3 | J38: 37 | K38: =IFERROR(__xludf.DUMMYFUNCTION("GOOGLETRANSLATE(B39, ""auto"", ""en"")"),"Threat research applications through bug reports") -> Threat research applications through bug reports | L38: =IFERROR(__xludf.DUMMYFUNCTION("GOOGLETRANSLATE(D39, ""auto"", ""en"")"),"The threat is the possibility to study the algorithm of the offender diskreditiruemogo application and its intended structure by analyzing generated by this application error reports. This threat is due to the placement of protected information (or infor"&"mation generalization which may disclose protected information system) in the generated error reports. Implementation of this threat is possible in case of access to the offender error reports, generated by the application, and the presence of the redund"&"ancy data they contain") -> The threat is the possibility to study the algorithm of the offender diskreditiruemogo application and its intended structure by analyzing generated by this application error reports. This threat is due to the placement of protected information (or information generalization which may disclose protected information system) in the generated error reports. Implementation of this threat is possible in case of access to the offender error reports, generated by the application, and the presence of the redundancy data they contain | M38: =IFERROR(__xludf.DUMMYFUNCTION("GOOGLETRANSLATE(F39, ""auto"", ""en"")"),"External intruder with an average potential intruder inner middle potential") -> External intruder with an average potential intruder inner middle potential | N38: =IFERROR(__xludf.DUMMYFUNCTION("GOOGLETRANSLATE(H39, ""auto"", ""en"")"),"System software, application software, network software, firmware") -> System software, application software, network software, firmware
B39: הדרכות | C39: חדירה מהאינטרנט ישירות לרשת הארגון | D39: איום חיצוני | E39: התחזות לארגון לצורך תקיפת ארגונים אחרים או משתמשים ספציפיים | F39: גישה פיזית, גישה או | G39: 3 | H39: 3 | J39: 38 | K39: =IFERROR(__xludf.DUMMYFUNCTION("GOOGLETRANSLATE(B40, ""auto"", ""en"")"),"The threat of the exhaustion of the computing resources of large data storage") -> The threat of the exhaustion of the computing resources of large data storage | L39: =IFERROR(__xludf.DUMMYFUNCTION("GOOGLETRANSLATE(D40, ""auto"", ""en"")"),"The threat is the possibility of occurrence of a temporary status such as ""denial of service"" from the storage of large data. This is due to the constant threat of difficult to control the filling of additional disk space at the expense of data is cont"&"inuously coming from different information sources, and the weakness of access technologies and storage of information in large data repositories. Implementation of this threat is possible while the instantaneous (current) exceeding the data rate over th"&"e rate of their conservation (because of insufficient capacity of the communication channel or the rate of release of free space and store it incoming data) or provided temporary lack of space in the store (because incorrect storage management or as a res"&"ult of the violator destructive effects on the software control mechanism for filling the storage by changing the parameters of operation or logic)") -> The threat is the possibility of occurrence of a temporary status such as "denial of service" from the storage of large data. This is due to the constant threat of difficult to control the filling of additional disk space at the expense of data is continuously coming from different information sources, and the weakness of access technologies and storage of information in large data repositories. Implementation of this threat is possible while the instantaneous (current) exceeding the data rate over the rate of their conservation (because of insufficient capacity of the communication channel or the rate of release of free space and store it incoming data) or provided temporary lack of space in the store (because incorrect storage management or as a result of the violator destructive effects on the software control mechanism for filling the storage by changing the parameters of operation or logic) | M39: =IFERROR(__xludf.DUMMYFUNCTION("GOOGLETRANSLATE(F40, ""auto"", ""en"")"),"Insider with a low potential") -> Insider with a low potential | N39: =IFERROR(__xludf.DUMMYFUNCTION("GOOGLETRANSLATE(H40, ""auto"", ""en"")"),"Information system") -> Information system
B40: הגנת תחנות עבודה ושרתים | C40: חדירה מהאינטרנט ישירות לרשת הארגון | D40: איום פנימי/חיצוני | E40: ניצול פגיעויות ידועות ולא ידועות בתוכנת המשתמש | F40: גישה פיזית, גישה ידועות | G40: 2 | H40: 3 | J40: 39 | K40: =IFERROR(__xludf.DUMMYFUNCTION("GOOGLETRANSLATE(B41, ""auto"", ""en"")"),"The threat of depletion of keys necessary to update the BIOS") -> The threat of depletion of keys necessary to update the BIOS | L40: =IFERROR(__xludf.DUMMYFUNCTION("GOOGLETRANSLATE(D41, ""auto"", ""en"")"),"The threat is the possibility of violation of (the impossibility of) procedures BIOS / UEFI updates with the exhaustion of the stock necessary for carrying out its keys. This threat is caused by a limited set of keys required for BIOS / UEFI update. Imp"&"lementation of this threat is possible by exploiting vulnerabilities means updates the set of keys, or through the use of offender key recovery software") -> The threat is the possibility of violation of (the impossibility of) procedures BIOS / UEFI updates with the exhaustion of the stock necessary for carrying out its keys. This threat is caused by a limited set of keys required for BIOS / UEFI update. Implementation of this threat is possible by exploiting vulnerabilities means updates the set of keys, or through the use of offender key recovery software | M40: =IFERROR(__xludf.DUMMYFUNCTION("GOOGLETRANSLATE(F41, ""auto"", ""en"")"),"The outer middle potential violator") -> The outer middle potential violator | N40: =IFERROR(__xludf.DUMMYFUNCTION("GOOGLETRANSLATE(H41, ""auto"", ""en"")"),"BIOS / UEFI firmware") -> BIOS / UEFI firmware
B41: הגנת תחנות עבודה ושרתים | C41: חדירה מהאינטרנט ישירות לרשת הארגון | D41: איום חיצוני | E41: שימוש בפרוטוקול לצורך חדירה לתחנת המשתמש והשתלטות | F41: גישה פיזית, גישה לתחנת | G41: 2 | H41: 2 | J41: 40 | K41: =IFERROR(__xludf.DUMMYFUNCTION("GOOGLETRANSLATE(B42, ""auto"", ""en"")"),"The threat of conflict of jurisdiction in different countries") -> The threat of conflict of jurisdiction in different countries | L41: =IFERROR(__xludf.DUMMYFUNCTION("GOOGLETRANSLATE(D42, ""auto"", ""en"")"),"The threat is the possibility of failure in the cross-border transfer of the protected information in the provision of cloud services in accordance with the local laws of the countries whose residents are involved in the delivery of cloud services. This "&"threat stems from the fact that, depending on the features of the legislation in different countries, the residents of which are involved in the delivery of cloud services, while ensuring information security can be used legal measures in different jurisd"&"ictions. Implementation of this threat is possible, provided that the information security in the course of providing cloud services imposed legal measures in different jurisdictions, conflicting in several issues") -> The threat is the possibility of failure in the cross-border transfer of the protected information in the provision of cloud services in accordance with the local laws of the countries whose residents are involved in the delivery of cloud services. This threat stems from the fact that, depending on the features of the legislation in different countries, the residents of which are involved in the delivery of cloud services, while ensuring information security can be used legal measures in different jurisdictions. Implementation of this threat is possible, provided that the information security in the course of providing cloud services imposed legal measures in different jurisdictions, conflicting in several issues | M41: =IFERROR(__xludf.DUMMYFUNCTION("GOOGLETRANSLATE(F42, ""auto"", ""en"")"),"External intruder with a low potential") -> External intruder with a low potential | N41: =IFERROR(__xludf.DUMMYFUNCTION("GOOGLETRANSLATE(H42, ""auto"", ""en"")"),"cloud system") -> cloud system
B42: שרשרת אספקה ומיקור חוץ | C42: חבלה בשרשרת אספקה | D42: כלל האיומים תחת "איום פנימי" | E42: כללי | F42: כללי | G42: 3 | H42: 3 | J42: 41 | K42: =IFERROR(__xludf.DUMMYFUNCTION("GOOGLETRANSLATE(B43, ""auto"", ""en"")"),"The threat of cross-site scripting") -> The threat of cross-site scripting | L42: =IFERROR(__xludf.DUMMYFUNCTION("GOOGLETRANSLATE(D43, ""auto"", ""en"")"),"The threat is the possibility of introducing the offender sections of malicious code to the site diskreditiruemoy system so that it will be executed on the workstation user is viewing this site. This threat is caused by security weaknesses verification m"&"echanism in the processing of requests and data from the Web site. Implementation of the threat is possible in case the client software supports the execution of scripts, and the offender is able to send queries and data diskreditiruemuyu system") -> The threat is the possibility of introducing the offender sections of malicious code to the site diskreditiruemoy system so that it will be executed on the workstation user is viewing this site. This threat is caused by security weaknesses verification mechanism in the processing of requests and data from the Web site. Implementation of the threat is possible in case the client software supports the execution of scripts, and the offender is able to send queries and data diskreditiruemuyu system | M42: =IFERROR(__xludf.DUMMYFUNCTION("GOOGLETRANSLATE(F43, ""auto"", ""en"")"),"External intruder with a low potential") -> External intruder with a low potential | N42: =IFERROR(__xludf.DUMMYFUNCTION("GOOGLETRANSLATE(H43, ""auto"", ""en"")"),"Network node, network software") -> Network node, network software
B43: מניעת קוד זדוני | C43: חבלה בשרשרת אספקה | D43: איום חיצוני | E43: החדרת נוזקה לארגון באמצעות גישה מרחוק | F43: גישה מרחוק | G43: 2 | H43: 1 | J43: 42 | K43: =IFERROR(__xludf.DUMMYFUNCTION("GOOGLETRANSLATE(B44, ""auto"", ""en"")"),"The threat of cross-site request forgery") -> The threat of cross-site request forgery | L43: =IFERROR(__xludf.DUMMYFUNCTION("GOOGLETRANSLATE(D44, ""auto"", ""en"")"),"The threat is the possibility of sending the offender diskreditiruemomu user references containing malicious web code resource, the transition to which will be automatically made illegal malicious actions on behalf of the user discredited. This threat is"&" caused by vulnerabilities browsers that allow you to perform actions without confirmation or authentication of the user diskreditiruemogo. Implementation of the threat is possible if the user saves diskreditiruemy authentication information using a web "&"browser") -> The threat is the possibility of sending the offender diskreditiruemomu user references containing malicious web code resource, the transition to which will be automatically made illegal malicious actions on behalf of the user discredited. This threat is caused by vulnerabilities browsers that allow you to perform actions without confirmation or authentication of the user diskreditiruemogo. Implementation of the threat is possible if the user saves diskreditiruemy authentication information using a web browser | M43: =IFERROR(__xludf.DUMMYFUNCTION("GOOGLETRANSLATE(F44, ""auto"", ""en"")"),"The outer middle potential violator") -> The outer middle potential violator | N43: =IFERROR(__xludf.DUMMYFUNCTION("GOOGLETRANSLATE(H44, ""auto"", ""en"")"),"Network node, network software") -> Network node, network software
B44: אבטחה ברכש ופיתוח | C44: חבלה בשרשרת אספקה | D44: איום חיצוני | E44: החדרת נוזקה לארגון באמצעות תוכנה מטופלת | F44: גישה מרחוק, גישה לאינטרנט, התקן חיצוני (דוגמת DOK, CD) | G44: 2 | H44: 3 | J44: 43 | K44: =IFERROR(__xludf.DUMMYFUNCTION("GOOGLETRANSLATE(B45, ""auto"", ""en"")"),"The threat of violation of the availability of the cloud server") -> The threat of violation of the availability of the cloud server | L44: =IFERROR(__xludf.DUMMYFUNCTION("GOOGLETRANSLATE(D45, ""auto"", ""en"")"),"The threat lies in the possibility of termination of cloud-based services to all customers (or customer group) due to violation of their access to cloud infrastructure. This threat stems from the fact that accessibility is not a specific requirement of i"&"nformation security for cloud computing, and, in addition, cloud systems are implemented in accordance with the service-oriented approach. Implementation of this threat is possible in the transition of one or more cloud servers in a state of ""denial of "&"service"". Moreover, the ability to dynamically change the amount of cloud-based services provided to consumers could be used by the offender to implement the threat. At the same time successfully realized the threat with respect to only one cloud service"&" will allow to disrupt the availability of the entire cloud system") -> The threat lies in the possibility of termination of cloud-based services to all customers (or customer group) due to violation of their access to cloud infrastructure. This threat stems from the fact that accessibility is not a specific requirement of information security for cloud computing, and, in addition, cloud systems are implemented in accordance with the service-oriented approach. Implementation of this threat is possible in the transition of one or more cloud servers in a state of "denial of service". Moreover, the ability to dynamically change the amount of cloud-based services provided to consumers could be used by the offender to implement the threat. At the same time successfully realized the threat with respect to only one cloud service will allow to disrupt the availability of the entire cloud system | M44: =IFERROR(__xludf.DUMMYFUNCTION("GOOGLETRANSLATE(F45, ""auto"", ""en"")"),"External intruder low potential insider with a low potential") -> External intruder low potential insider with a low potential | N44: =IFERROR(__xludf.DUMMYFUNCTION("GOOGLETRANSLATE(H45, ""auto"", ""en"")"),"Cloud computing, cloud server") -> Cloud computing, cloud server
B45: שרשרת אספקה ומיקור חוץ | C45: חבלה בשרשרת אספקה | D45: איום חיצוני | E45: העתקת מידע של הארגון ללקוח אחר | F45: גישה מרחוק, גישה רשתית | G45: 2 | H45: 2 | J45: 44 | K45: =IFERROR(__xludf.DUMMYFUNCTION("GOOGLETRANSLATE(B46, ""auto"", ""en"")"),"The threat of violation of the isolation of user data inside a virtual machine") -> The threat of violation of the isolation of user data inside a virtual machine | L45: =IFERROR(__xludf.DUMMYFUNCTION("GOOGLETRANSLATE(D46, ""auto"", ""en"")"),"The threat is the possibility of a security breach programs, user data, operating within a virtual machine with malicious software that functions outside of the virtual machine. This threat is due to the presence of the vulnerabilities of software hyperv"&"isor providing isolation address space used to store user data programs operating within the virtual machine, from unauthorized access by malicious software, virtual machine is functioning. Implementation of this threat can be provided successfully overc"&"ome the malware code boundaries of the virtual machine is not only due to the operation of the hypervisor vulnerabilities, but also by the implementation of such an impact with the lower (with respect to the hypervisor) system performance levels") -> The threat is the possibility of a security breach programs, user data, operating within a virtual machine with malicious software that functions outside of the virtual machine. This threat is due to the presence of the vulnerabilities of software hypervisor providing isolation address space used to store user data programs operating within the virtual machine, from unauthorized access by malicious software, virtual machine is functioning. Implementation of this threat can be provided successfully overcome the malware code boundaries of the virtual machine is not only due to the operation of the hypervisor vulnerabilities, but also by the implementation of such an impact with the lower (with respect to the hypervisor) system performance levels | M45: =IFERROR(__xludf.DUMMYFUNCTION("GOOGLETRANSLATE(F46, ""auto"", ""en"")"),"External intruder with an average potential intruder inner middle potential") -> External intruder with an average potential intruder inner middle potential | N45: =IFERROR(__xludf.DUMMYFUNCTION("GOOGLETRANSLATE(H46, ""auto"", ""en"")"),"Virtual machine hypervisor") -> Virtual machine hypervisor
B46: אבטחה ברכש ופיתוח | C46: חדירה מהאינטרנט ישירות לרשת הארגון | D46: איום חיצוני | E46: פיתוח מוצר תוכנה עבור הארגון המכיל חולשות מהותיות המנוצלות לרעה (דוגמת Back door) | F46: גישה מרחוק, גישה רשתית | G46: 3 | H46: 3 | J46: 45 | K46: =IFERROR(__xludf.DUMMYFUNCTION("GOOGLETRANSLATE(B47, ""auto"", ""en"")"),"violations of the threat of isolation BIOS runtime") -> violations of the threat of isolation BIOS runtime | L46: =IFERROR(__xludf.DUMMYFUNCTION("GOOGLETRANSLATE(D47, ""auto"", ""en"")"),"The threat is the possibility of changing the parameters and (or) the software of the operating logic BIOS / UEFI software by the impact of the computer's operating system or by unauthorized access to the channel networking server service processor. This"&" threat is caused by weaknesses technologies restricting access to the BIOS / UEFI, its administrative functions and updates from the operating system or communication channels. The implementation of this possible threat: from the operating system - pro"&"vided there BIOS / UEFI functional updates and (or) management software BIOS / UEFI software from the operating system; the network side - on condition that the server diskreditiruemogo service processor sufficient privileges to control the entire system"&", including the BIOS / UEFI modification system servers and server diskreditiruemogo") -> The threat is the possibility of changing the parameters and (or) the software of the operating logic BIOS / UEFI software by the impact of the computer's operating system or by unauthorized access to the channel networking server service processor. This threat is caused by weaknesses technologies restricting access to the BIOS / UEFI, its administrative functions and updates from the operating system or communication channels. The implementation of this possible threat: from the operating system - provided there BIOS / UEFI functional updates and (or) management software BIOS / UEFI software from the operating system; the network side - on condition that the server diskreditiruemogo service processor sufficient privileges to control the entire system, including the BIOS / UEFI modification system servers and server diskreditiruemogo | M46: =IFERROR(__xludf.DUMMYFUNCTION("GOOGLETRANSLATE(F47, ""auto"", ""en"")"),"Insider with a low potential") -> Insider with a low potential | N46: =IFERROR(__xludf.DUMMYFUNCTION("GOOGLETRANSLATE(H47, ""auto"", ""en"")"),"Firmware and BIOS / UEFI hardware") -> Firmware and BIOS / UEFI hardware
B47: המשכיות עסקית | C47: פגיעה בזמינות עקב מפגע סביבתי | D47: גורם עליון | E47: נסיבות קיצוניות הנגרמות בשל תופעות טבע היוצרות הצפה/שיטפון ופגיעה במתקן ואו נכסים חשובים | F47: גישה פיזית | G47: 1 | H47: 1 | J47: 46 | K47: =IFERROR(__xludf.DUMMYFUNCTION("GOOGLETRANSLATE(B48, ""auto"", ""en"")"),"The threat of violation of the virtual authentication information interaction subjects of procedures") -> The threat of violation of the virtual authentication information interaction subjects of procedures | L47: =IFERROR(__xludf.DUMMYFUNCTION("GOOGLETRANSLATE(D48, ""auto"", ""en"")"),"The threat lies in the possibility of substitution of the subject virtual interaction information, as well as the possibility of occurrence of the failure condition such interaction. This threat is due to the presence of a plurality of different protocol"&"s mutual identification and authentication of virtual, virtualized entities and physical access, interact with each other during data transfer within a single virtual infrastructure level and between its layers. Implementation of this threat is possible "&"in case of an error during the authentication of the virtual information interaction subjects") -> The threat lies in the possibility of substitution of the subject virtual interaction information, as well as the possibility of occurrence of the failure condition such interaction. This threat is due to the presence of a plurality of different protocols mutual identification and authentication of virtual, virtualized entities and physical access, interact with each other during data transfer within a single virtual infrastructure level and between its layers. Implementation of this threat is possible in case of an error during the authentication of the virtual information interaction subjects | M47: =IFERROR(__xludf.DUMMYFUNCTION("GOOGLETRANSLATE(F48, ""auto"", ""en"")"),"External intruder low potential insider with a low potential") -> External intruder low potential insider with a low potential | N47: =IFERROR(__xludf.DUMMYFUNCTION("GOOGLETRANSLATE(H48, ""auto"", ""en"")"),"Network node, network software, metadata, user data usernames") -> Network node, network software, metadata, user data usernames
B48: המשכיות עסקית | C48: פגיעה בזמינות עקב מפגע סביבתי | D48: גורם עליון | E48: נסיבות קיצוניות הנגרמות בשל תופעות טבע היוצרות רעידת אדמה ופגיעה פיזית במתקן | F48: גישה פיזית | G48: 1 | H48: 1 | J48: 47 | K48: =IFERROR(__xludf.DUMMYFUNCTION("GOOGLETRANSLATE(B49, ""auto"", ""en"")"),"The threat of failure of performance of grid system with atypical network load") -> The threat of failure of performance of grid system with atypical network load | L48: =IFERROR(__xludf.DUMMYFUNCTION("GOOGLETRANSLATE(D49, ""auto"", ""en"")"),"The threat lies in the possibility of a significant reduction in productivity grid system until the temporary disruption of her health when a network load atypical (including induced distributed DoS-attack activity of other network users, and others.). T"&"his threat is caused by the weakness of grid computing technology - performance grid system has a strong dependence on the load of the communication channels, which is a consequence of maximum territorial distributed computing unit grid system to all type"&"s of information systems. Implementation of this threat can be subject to a lack of control of the state of individual nodes grid system by the manager of Grid system tasks") -> The threat lies in the possibility of a significant reduction in productivity grid system until the temporary disruption of her health when a network load atypical (including induced distributed DoS-attack activity of other network users, and others.). This threat is caused by the weakness of grid computing technology - performance grid system has a strong dependence on the load of the communication channels, which is a consequence of maximum territorial distributed computing unit grid system to all types of information systems. Implementation of this threat can be subject to a lack of control of the state of individual nodes grid system by the manager of Grid system tasks | M48: =IFERROR(__xludf.DUMMYFUNCTION("GOOGLETRANSLATE(F49, ""auto"", ""en"")"),"External intruder with an average potential intruder inner middle potential") -> External intruder with an average potential intruder inner middle potential | N48: =IFERROR(__xludf.DUMMYFUNCTION("GOOGLETRANSLATE(H49, ""auto"", ""en"")"),"Grid system, network traffic") -> Grid system, network traffic
B49: המשכיות עסקית | C49: פגיעה בזמינות עקב מפגע סביבתי | D49: גורם עליון | E49: נסיבות קיצוניות הנגרמות בשל תופעות טבע היוצרות שריפה ופגיעה במתקן ואו נכסים חשובים | F49: גישה פיזית | G49: 2 | H49: 2 | J49: 48 | K49: =IFERROR(__xludf.DUMMYFUNCTION("GOOGLETRANSLATE(B50, ""auto"", ""en"")"),"The threat of violation of information processing by unauthorized changes to the virtual machine images") -> The threat of violation of information processing by unauthorized changes to the virtual machine images | L49: =IFERROR(__xludf.DUMMYFUNCTION("GOOGLETRANSLATE(D50, ""auto"", ""en"")"),"The threat is the possibility of a destructive impact on the software diskreditiruemuyu or indirect exposure to destructive software through it to other systems by means of unauthorized access to a virtual machine image. This threat is caused by weakness"&" of measures restricting access to the images of virtual machines implemented in software virtualization. Implementation of this threat can cause: to a violation of privacy protected information processed by using virtual machines created on the basis o"&"f illegally altered images; to the integrity of the programs that are installed on virtual machines; to a breach of the availability of virtual machine resources; to create a botnet through the introduction of malicious software in virtual machine imag"&"es to be used as templates (reference images)") -> The threat is the possibility of a destructive impact on the software diskreditiruemuyu or indirect exposure to destructive software through it to other systems by means of unauthorized access to a virtual machine image. This threat is caused by weakness of measures restricting access to the images of virtual machines implemented in software virtualization. Implementation of this threat can cause: to a violation of privacy protected information processed by using virtual machines created on the basis of illegally altered images; to the integrity of the programs that are installed on virtual machines; to a breach of the availability of virtual machine resources; to create a botnet through the introduction of malicious software in virtual machine images to be used as templates (reference images) | M49: =IFERROR(__xludf.DUMMYFUNCTION("GOOGLETRANSLATE(F50, ""auto"", ""en"")"),"External intruder with an average potential intruder inner middle potential") -> External intruder with an average potential intruder inner middle potential | N49: =IFERROR(__xludf.DUMMYFUNCTION("GOOGLETRANSLATE(H50, ""auto"", ""en"")"),"The image of the virtual machine, the network node, network software, virtual machine") -> The image of the virtual machine, the network node, network software, virtual machine
B50: המשכיות עסקית | C50: פגיעה בזמינות עקב מפגע סביבתי | D50: גורם עליון | E50: נסיבות קיצוניות הנגרמות בשל תופעות טבע היוצרות סערת ברקים והפרעות סטטיות ואו פגיעה במתקני שידור | F50: גישה פיזית | G50: 2 | H50: 1 | J50: 49 | K50: =IFERROR(__xludf.DUMMYFUNCTION("GOOGLETRANSLATE(B51, ""auto"", ""en"")"),"The threat of compromising the integrity of the data cache") -> The threat of compromising the integrity of the data cache | L50: =IFERROR(__xludf.DUMMYFUNCTION("GOOGLETRANSLATE(D51, ""auto"", ""en"")"),"The threat is the possibility of placing the offender in the cache of the application (eg, browser) or services (eg, DNS or ARP) incorrect (potentially dangerous) data in such a way that prior to updating the cache diskreditiruemoe application (or service"&") will read this data correct. This threat is caused by weaknesses in the mechanism of monitoring the integrity of data in the cache. Implementation of this threat can be made to the conditions of the intruder successfully unauthorized access to the dat"&"a cache and the absence of an integrity check of data in the cache by diskreditiruemogo application (or service)") -> The threat is the possibility of placing the offender in the cache of the application (eg, browser) or services (eg, DNS or ARP) incorrect (potentially dangerous) data in such a way that prior to updating the cache diskreditiruemoe application (or service) will read this data correct. This threat is caused by weaknesses in the mechanism of monitoring the integrity of data in the cache. Implementation of this threat can be made to the conditions of the intruder successfully unauthorized access to the data cache and the absence of an integrity check of data in the cache by diskreditiruemogo application (or service) | M50: =IFERROR(__xludf.DUMMYFUNCTION("GOOGLETRANSLATE(F51, ""auto"", ""en"")"),"External intruder low potential insider with a low potential") -> External intruder low potential insider with a low potential | N50: =IFERROR(__xludf.DUMMYFUNCTION("GOOGLETRANSLATE(H51, ""auto"", ""en"")"),"Networking software") -> Networking software
B51: המשכיות עסקית | C51: פגיעה בזמינות עקב מפגע סביבתי | D51: גורם עליון | E51: נסיבות קיצוניות הנגרמות בשל תופעות טבע היוצרות כשל באספקת חשמל ברמה הלאומית ואו המקומית | F51: גישה פיזית | G51: 2 | H51: 1 | J51: 50 | K51: =IFERROR(__xludf.DUMMYFUNCTION("GOOGLETRANSLATE(B52, ""auto"", ""en"")"),"The threat of an incorrect definition of the format input data entering the storage of large data") -> The threat of an incorrect definition of the format input data entering the storage of large data | L51: =IFERROR(__xludf.DUMMYFUNCTION("GOOGLETRANSLATE(D52, ""auto"", ""en"")"),"The threat is the possibility of distortion of information, stored in large data warehouse, or refuse to conduct conservation when transferring data to it in several formats. This threat is caused by weakness of technology determine the format of the inp"&"ut data based on the additional service information (header files and network packets, file extensions, etc.), and adaptive technology selection and application of multi-format data processing techniques in large data repositories. Implementation of this"&" threat can be provided that the additional service information about the database for any reason, does not correspond to their actual content, or in the storage of large data is not implemented data processing method receives format") -> The threat is the possibility of distortion of information, stored in large data warehouse, or refuse to conduct conservation when transferring data to it in several formats. This threat is caused by weakness of technology determine the format of the input data based on the additional service information (header files and network packets, file extensions, etc.), and adaptive technology selection and application of multi-format data processing techniques in large data repositories. Implementation of this threat can be provided that the additional service information about the database for any reason, does not correspond to their actual content, or in the storage of large data is not implemented data processing method receives format | M51: =IFERROR(__xludf.DUMMYFUNCTION("GOOGLETRANSLATE(F52, ""auto"", ""en"")"),"Insider with a low potential") -> Insider with a low potential | N51: =IFERROR(__xludf.DUMMYFUNCTION("GOOGLETRANSLATE(H52, ""auto"", ""en"")"),"Storage of large data, metadata,") -> Storage of large data, metadata,
B52: המשכיות עסקית | C52: פגיעה בזמינות עקב מפגע סביבתי | D52: גורם עליון | E52: נסיבות קיצוניות הנגרמות בשל תופעות טבע היוצרות כשל בממשק טלפוניה ציבורית | F52: גישה פיזית | G52: 1 | H52: 1 | J52: 51 | K52: =IFERROR(__xludf.DUMMYFUNCTION("GOOGLETRANSLATE(B53, ""auto"", ""en"")"),"The threat of impossibility of restoration work session on the PC when outputting of the intermediate power states") -> The threat of impossibility of restoration work session on the PC when outputting of the intermediate power states | L52: =IFERROR(__xludf.DUMMYFUNCTION("GOOGLETRANSLATE(D53, ""auto"", ""en"")"),"The threat is the possibility of losing unsaved data processed in the previous session on the computer, as well as the possibility of loss of time for the resumption of work on the computer. This threat is due to errors in the implementation of computer "&"software and hardware components associated with providing power. Implementation of this threat is possible while the computer could not derive from the intermediate power state ( ""standby mode"", ""hibernation"", etc.).") -> The threat is the possibility of losing unsaved data processed in the previous session on the computer, as well as the possibility of loss of time for the resumption of work on the computer. This threat is due to errors in the implementation of computer software and hardware components associated with providing power. Implementation of this threat is possible while the computer could not derive from the intermediate power state ( "standby mode", "hibernation", etc.). | M52: =IFERROR(__xludf.DUMMYFUNCTION("GOOGLETRANSLATE(F53, ""auto"", ""en"")"),"Insider with a low potential") -> Insider with a low potential | N52: =IFERROR(__xludf.DUMMYFUNCTION("GOOGLETRANSLATE(H53, ""auto"", ""en"")"),"Workstation, data carrier, system software, metadata, file system objects, the registry") -> Workstation, data carrier, system software, metadata, file system objects, the registry
B53: המשכיות עסקית | C53: פגיעה בזמינות עקב מפגע סביבתי | D53: גורם עליון | E53: נסיבות קיצוניות הנגרמות בשל תופעות טבע היוצרות כשל בממשק תקשורת לאינטרנט | F53: גישה פיזית | G53: 1 | H53: 2 | J53: 52 | K53: =IFERROR(__xludf.DUMMYFUNCTION("GOOGLETRANSLATE(B54, ""auto"", ""en"")"),"The threat of inability to migration of virtual machines because of the incompatibility of hardware and software") -> The threat of inability to migration of virtual machines because of the incompatibility of hardware and software | L53: =IFERROR(__xludf.DUMMYFUNCTION("GOOGLETRANSLATE(D54, ""auto"", ""en"")"),"The threat is the possibility of the consumer of cloud services insurmountable difficulties to change the provider of cloud services due to technical difficulties in the implementation of procedures migration of virtual machine images from a single vendor"&" cloud system cloud services in the other. This threat stems from the fact that each provider of cloud-based services are used to implement its activities hardware and software from different manufacturers, some of which may use specific (for the produce"&"r) instructions, protocols, methods, switching circuits and other features of the implementation of its functionality. Implementation of this threat is possible in case of incompatibility between standard (API) data exchange APIs to implement procedures "&"for migration of virtual machine images between different cloud providers in one or both directions. Also, this threat stipulates restriction of the possibility of changing hardware manufacturers and software provider of cloud services, which could lead "&"to a breach of the integrity and availability of information on the fault of the supplier of cloud services") -> The threat is the possibility of the consumer of cloud services insurmountable difficulties to change the provider of cloud services due to technical difficulties in the implementation of procedures migration of virtual machine images from a single vendor cloud system cloud services in the other. This threat stems from the fact that each provider of cloud-based services are used to implement its activities hardware and software from different manufacturers, some of which may use specific (for the producer) instructions, protocols, methods, switching circuits and other features of the implementation of its functionality. Implementation of this threat is possible in case of incompatibility between standard (API) data exchange APIs to implement procedures for migration of virtual machine images between different cloud providers in one or both directions. Also, this threat stipulates restriction of the possibility of changing hardware manufacturers and software provider of cloud services, which could lead to a breach of the integrity and availability of information on the fault of the supplier of cloud services | M53: =IFERROR(__xludf.DUMMYFUNCTION("GOOGLETRANSLATE(F54, ""auto"", ""en"")"),"External intruder with a low potential") -> External intruder with a low potential | N53: =IFERROR(__xludf.DUMMYFUNCTION("GOOGLETRANSLATE(H54, ""auto"", ""en"")"),"Cloud infrastructure, virtual machine hardware, system software") -> Cloud infrastructure, virtual machine hardware, system software
J54: 53 | K54: =IFERROR(__xludf.DUMMYFUNCTION("GOOGLETRANSLATE(B55, ""auto"", ""en"")"),"The threat of inability to control user rights BIOS") -> The threat of inability to control user rights BIOS | L54: =IFERROR(__xludf.DUMMYFUNCTION("GOOGLETRANSLATE(D55, ""auto"", ""en"")"),"The threat is the possibility of BIOS / UEFI misuse of users declared functional-oriented administrators. This threat is caused by weakness of access control technology (distribution rights) to the BIOS / UEFI functionality between users and administrato"&"rs. Implementation of this threat can be provided physical access to the terminal and, if necessary, to the computer system unit") -> The threat is the possibility of BIOS / UEFI misuse of users declared functional-oriented administrators. This threat is caused by weakness of access control technology (distribution rights) to the BIOS / UEFI functionality between users and administrators. Implementation of this threat can be provided physical access to the terminal and, if necessary, to the computer system unit | M54: =IFERROR(__xludf.DUMMYFUNCTION("GOOGLETRANSLATE(F55, ""auto"", ""en"")"),"Insider with a low potential") -> Insider with a low potential | N54: =IFERROR(__xludf.DUMMYFUNCTION("GOOGLETRANSLATE(H55, ""auto"", ""en"")"),"BIOS / UEFI firmware") -> BIOS / UEFI firmware
J55: 54 | K55: =IFERROR(__xludf.DUMMYFUNCTION("GOOGLETRANSLATE(B56, ""auto"", ""en"")"),"unfair execution threat of suppliers of cloud services") -> unfair execution threat of suppliers of cloud services | L55: =IFERROR(__xludf.DUMMYFUNCTION("GOOGLETRANSLATE(D56, ""auto"", ""en"")"),"The threat is the ability to expand or damage to the integrity of the cloud service provider protected information consumer cloud services, the default quality requirements (accessibility level) provided by cloud consumers access to their services and pro"&"grams to immigrate into the cloud information systems. This threat is due to the impossibility of direct control over the actions of the supplier of cloud services from their consumers. Implementation of this threat is possible in cases of negligence on"&" the part of the supplier's cloud services, failure of officials and other employees of these instructions, failure measures for the management and security of cloud services, etc.") -> The threat is the ability to expand or damage to the integrity of the cloud service provider protected information consumer cloud services, the default quality requirements (accessibility level) provided by cloud consumers access to their services and programs to immigrate into the cloud information systems. This threat is due to the impossibility of direct control over the actions of the supplier of cloud services from their consumers. Implementation of this threat is possible in cases of negligence on the part of the supplier's cloud services, failure of officials and other employees of these instructions, failure measures for the management and security of cloud services, etc. | M55: =IFERROR(__xludf.DUMMYFUNCTION("GOOGLETRANSLATE(F56, ""auto"", ""en"")"),"External intruder with a low potential") -> External intruder with a low potential | N55: =IFERROR(__xludf.DUMMYFUNCTION("GOOGLETRANSLATE(H56, ""auto"", ""en"")"),"Information system, server, storage media, metadata, file system objects") -> Information system, server, storage media, metadata, file system objects
J56: 55 | K56: =IFERROR(__xludf.DUMMYFUNCTION("GOOGLETRANSLATE(B57, ""auto"", ""en"")"),"The threat of unprotected administration of cloud services") -> The threat of unprotected administration of cloud services | L56: =IFERROR(__xludf.DUMMYFUNCTION("GOOGLETRANSLATE(D57, ""auto"", ""en"")"),"The threat is the possibility of indirect destructive effects of the program on a part or all of the information systems operating in the cloud, by getting control over the cloud infrastructure through a remote administration mechanisms. This threat is c"&"aused by lack of attention given to the input control of the user data cloud services (including authentication data), as well as the vulnerability of unsafe data exchange interface (the API), used by remote administration tools. Implementation of this t"&"hreat is possible in the case of the infringer authentication information (when entering in public places) legitimate users, or exploitation of vulnerabilities in the means of remote administration") -> The threat is the possibility of indirect destructive effects of the program on a part or all of the information systems operating in the cloud, by getting control over the cloud infrastructure through a remote administration mechanisms. This threat is caused by lack of attention given to the input control of the user data cloud services (including authentication data), as well as the vulnerability of unsafe data exchange interface (the API), used by remote administration tools. Implementation of this threat is possible in the case of the infringer authentication information (when entering in public places) legitimate users, or exploitation of vulnerabilities in the means of remote administration | M56: =IFERROR(__xludf.DUMMYFUNCTION("GOOGLETRANSLATE(F57, ""auto"", ""en"")"),"External intruder low potential insider with a low potential") -> External intruder low potential insider with a low potential | N56: =IFERROR(__xludf.DUMMYFUNCTION("GOOGLETRANSLATE(H57, ""auto"", ""en"")"),"Cloud system, workstation, network software") -> Cloud system, workstation, network software
J57: 56 | K57: =IFERROR(__xludf.DUMMYFUNCTION("GOOGLETRANSLATE(B58, ""auto"", ""en"")"),"The threat of poor infrastructure migration to the cloud") -> The threat of poor infrastructure migration to the cloud | L57: =IFERROR(__xludf.DUMMYFUNCTION("GOOGLETRANSLATE(D58, ""auto"", ""en"")"),"The threat is the possibility of reducing the real level of security of immigrating to the cloud information system due to errors made in migration in the transformation of its physical infrastructure to the cloud. This threat stems from the fact that ev"&"en the conversion of the information system infrastructure to the cloud often requires major changes in this infrastructure (eg in security policies and the organization of the network of data exchange). Implementation of this threat is possible in case "&"of incompatibility of software and network interfaces or inconsistencies in the implementation of security policies in the cloud migration information system") -> The threat is the possibility of reducing the real level of security of immigrating to the cloud information system due to errors made in migration in the transformation of its physical infrastructure to the cloud. This threat stems from the fact that even the conversion of the information system infrastructure to the cloud often requires major changes in this infrastructure (eg in security policies and the organization of the network of data exchange). Implementation of this threat is possible in case of incompatibility of software and network interfaces or inconsistencies in the implementation of security policies in the cloud migration information system | M57: =IFERROR(__xludf.DUMMYFUNCTION("GOOGLETRANSLATE(F58, ""auto"", ""en"")"),"External intruder with a low potential") -> External intruder with a low potential | N57: =IFERROR(__xludf.DUMMYFUNCTION("GOOGLETRANSLATE(H58, ""auto"", ""en"")"),"Information system, immigrated to the cloud, the cloud system") -> Information system, immigrated to the cloud, the cloud system
J58: 57 | K58: =IFERROR(__xludf.DUMMYFUNCTION("GOOGLETRANSLATE(B59, ""auto"", ""en"")"),"The threat of uncontrolled copying of data within the storage of large data") -> The threat of uncontrolled copying of data within the storage of large data | L58: =IFERROR(__xludf.DUMMYFUNCTION("GOOGLETRANSLATE(D59, ""auto"", ""en"")"),"The threat lies in the complexity of the control of all copies of the automatically generated information in large data warehouse for temporary data inconsistencies operations. This threat caused by the implementation of the duplication (two- or multiple"&") data on a variety of computing nodes that are part of large data repository, in order to increase access to this data for a large number of read / write requests speed. In this case, the operation is an inner function and ""opaque"" for end users and ad"&"ministrators of large data storage. Implementation of this threat can be provided insufficient measures to control the automatically generated data copies used in large data warehouse") -> The threat lies in the complexity of the control of all copies of the automatically generated information in large data warehouse for temporary data inconsistencies operations. This threat caused by the implementation of the duplication (two- or multiple) data on a variety of computing nodes that are part of large data repository, in order to increase access to this data for a large number of read / write requests speed. In this case, the operation is an inner function and "opaque" for end users and administrators of large data storage. Implementation of this threat can be provided insufficient measures to control the automatically generated data copies used in large data warehouse | M58: =IFERROR(__xludf.DUMMYFUNCTION("GOOGLETRANSLATE(F59, ""auto"", ""en"")"),"Insider with a low potential") -> Insider with a low potential | N58: =IFERROR(__xludf.DUMMYFUNCTION("GOOGLETRANSLATE(H59, ""auto"", ""en"")"),"Storage of large data, metadata, data is protected") -> Storage of large data, metadata, data is protected
J59: 58 | K59: =IFERROR(__xludf.DUMMYFUNCTION("GOOGLETRANSLATE(B60, ""auto"", ""en"")"),"The threat of uncontrolled growth of virtual machines") -> The threat of uncontrolled growth of virtual machines | L59: =IFERROR(__xludf.DUMMYFUNCTION("GOOGLETRANSLATE(D60, ""auto"", ""en"")"),"The threat is the possibility of limiting or violation availability virtual resources for consumers of cloud services by accidental or unauthorized deliberate creation violator multiple virtual machines. This threat is due to a limited amount of disk spa"&"ce allocated for virtual infrastructure, and weaknesses of the process control technology to create virtual machines. Implementation of this threat is possible on condition that the infringer to create virtual machines in the cloud infrastructure") -> The threat is the possibility of limiting or violation availability virtual resources for consumers of cloud services by accidental or unauthorized deliberate creation violator multiple virtual machines. This threat is due to a limited amount of disk space allocated for virtual infrastructure, and weaknesses of the process control technology to create virtual machines. Implementation of this threat is possible on condition that the infringer to create virtual machines in the cloud infrastructure | M59: =IFERROR(__xludf.DUMMYFUNCTION("GOOGLETRANSLATE(F60, ""auto"", ""en"")"),"External intruder low potential insider with a low potential") -> External intruder low potential insider with a low potential | N59: =IFERROR(__xludf.DUMMYFUNCTION("GOOGLETRANSLATE(H60, ""auto"", ""en"")"),"Cloud system Management Console cloud infrastructure, cloud infrastructure") -> Cloud system Management Console cloud infrastructure, cloud infrastructure
J60: 59 | K60: =IFERROR(__xludf.DUMMYFUNCTION("GOOGLETRANSLATE(B61, ""auto"", ""en"")"),"The threat of uncontrolled growth in the number of reserved computing resources") -> The threat of uncontrolled growth in the number of reserved computing resources | L60: =IFERROR(__xludf.DUMMYFUNCTION("GOOGLETRANSLATE(D61, ""auto"", ""en"")"),"The threat is the possibility of failure of legal users to allocate computing resources after the offender undue redundancy of all available computing resources (computing resources and storage resources). This threat is caused by software vulnerabilitie"&"s level of virtual infrastructure management, realizing the function of the distribution of computing resources between users. Implementation of this threat can be subject to the successful implementation of the intruder unauthorized access to software v"&"irtual infrastructure management level, implements the functions of computing resources between users") -> The threat is the possibility of failure of legal users to allocate computing resources after the offender undue redundancy of all available computing resources (computing resources and storage resources). This threat is caused by software vulnerabilities level of virtual infrastructure management, realizing the function of the distribution of computing resources between users. Implementation of this threat can be subject to the successful implementation of the intruder unauthorized access to software virtual infrastructure management level, implements the functions of computing resources between users | M60: =IFERROR(__xludf.DUMMYFUNCTION("GOOGLETRANSLATE(F61, ""auto"", ""en"")"),"External intruder low potential insider with a low potential") -> External intruder low potential insider with a low potential | N60: =IFERROR(__xludf.DUMMYFUNCTION("GOOGLETRANSLATE(H61, ""auto"", ""en"")"),"Information system server") -> Information system server
J61: 60 | K61: =IFERROR(__xludf.DUMMYFUNCTION("GOOGLETRANSLATE(B62, ""auto"", ""en"")"),"The threat of uncontrolled destruction of data storage for large data") -> The threat of uncontrolled destruction of data storage for large data | L61: =IFERROR(__xludf.DUMMYFUNCTION("GOOGLETRANSLATE(D62, ""auto"", ""en"")"),"The threat is the possibility of deletion from the repository of some of the processed data, without the end user or the administrator is notified. This threat is due to the weaknesses of the mechanism of automatic deletion of data that do not meet certa"&"in requirements (limit ""lifetime"" in the store, the ultimate inconsistency with other data, create a copy in a different place, etc.). Implementation of this threat can be subject to failure, realized in large data storage control measures for the auto"&"matic deletion of data") -> The threat is the possibility of deletion from the repository of some of the processed data, without the end user or the administrator is notified. This threat is due to the weaknesses of the mechanism of automatic deletion of data that do not meet certain requirements (limit "lifetime" in the store, the ultimate inconsistency with other data, create a copy in a different place, etc.). Implementation of this threat can be subject to failure, realized in large data storage control measures for the automatic deletion of data | M61: =IFERROR(__xludf.DUMMYFUNCTION("GOOGLETRANSLATE(F62, ""auto"", ""en"")"),"Insider with a low potential") -> Insider with a low potential | N61: =IFERROR(__xludf.DUMMYFUNCTION("GOOGLETRANSLATE(H62, ""auto"", ""en"")"),"Storage of large data, metadata, data is protected") -> Storage of large data, metadata, data is protected
J62: 61 | K62: =IFERROR(__xludf.DUMMYFUNCTION("GOOGLETRANSLATE(B63, ""auto"", ""en"")"),"The threat of incorrect reference data transaction structure") -> The threat of incorrect reference data transaction structure | L62: =IFERROR(__xludf.DUMMYFUNCTION("GOOGLETRANSLATE(D63, ""auto"", ""en"")"),"The threat is the possibility of a perpetrator (the database client) fraud by interrupting the transaction or the transaction ID spoofing. In the first case there is an incomplete execution of transactions, and in the second - the user completes the trans"&"action by force, changing its ID, and reported that the transaction was not carried out, thereby causing repeated carrying out the transaction. This threat is caused by weakness of continuity mechanism to monitor transactions and the integrity of data tr"&"ansmitted during the transaction between the database and its client") -> The threat is the possibility of a perpetrator (the database client) fraud by interrupting the transaction or the transaction ID spoofing. In the first case there is an incomplete execution of transactions, and in the second - the user completes the transaction by force, changing its ID, and reported that the transaction was not carried out, thereby causing repeated carrying out the transaction. This threat is caused by weakness of continuity mechanism to monitor transactions and the integrity of data transmitted during the transaction between the database and its client | M62: =IFERROR(__xludf.DUMMYFUNCTION("GOOGLETRANSLATE(F63, ""auto"", ""en"")"),"The inner middle potential violator") -> The inner middle potential violator | N62: =IFERROR(__xludf.DUMMYFUNCTION("GOOGLETRANSLATE(H63, ""auto"", ""en"")"),"Network traffic, database, network software") -> Network traffic, database, network software
J63: 62 | K63: =IFERROR(__xludf.DUMMYFUNCTION("GOOGLETRANSLATE(B64, ""auto"", ""en"")"),"The threat of improper use of a transparent proxy server due to browser plugins") -> The threat of improper use of a transparent proxy server due to browser plugins | L63: =IFERROR(__xludf.DUMMYFUNCTION("GOOGLETRANSLATE(D64, ""auto"", ""en"")"),"The threat is the ability to redirect or copy data to be processed by the browser through a transparent proxy server, connected to a browser as a plugin. This threat is caused by weaknesses in access control mechanism browser settings. Realization is po"&"ssible in the event of the successful implementation of the infringer enable usage mode transparent proxy in the browser settings, for example, as a result of the threat of cross-site scripting") -> The threat is the ability to redirect or copy data to be processed by the browser through a transparent proxy server, connected to a browser as a plugin. This threat is caused by weaknesses in access control mechanism browser settings. Realization is possible in the event of the successful implementation of the infringer enable usage mode transparent proxy in the browser settings, for example, as a result of the threat of cross-site scripting | M63: =IFERROR(__xludf.DUMMYFUNCTION("GOOGLETRANSLATE(F64, ""auto"", ""en"")"),"External intruder with a low potential") -> External intruder with a low potential | N63: =IFERROR(__xludf.DUMMYFUNCTION("GOOGLETRANSLATE(H64, ""auto"", ""en"")"),"Networking software") -> Networking software
J64: 63 | K64: =IFERROR(__xludf.DUMMYFUNCTION("GOOGLETRANSLATE(B65, ""auto"", ""en"")"),"The threat of incorrect use of functional software and hardware") -> The threat of incorrect use of functional software and hardware | L64: =IFERROR(__xludf.DUMMYFUNCTION("GOOGLETRANSLATE(D65, ""auto"", ""en"")"),"The threat is the possibility of using the declared capabilities of software and hardware specific (non-standard, incorrect) manner to the destructive impact on the information system and processed information it. This threat associated with weaknesses p"&"rocessing mechanism and commands entered by users. Implementation of this threat is possible in the case of the offender access to hardware and software") -> The threat is the possibility of using the declared capabilities of software and hardware specific (non-standard, incorrect) manner to the destructive impact on the information system and processed information it. This threat associated with weaknesses processing mechanism and commands entered by users. Implementation of this threat is possible in the case of the offender access to hardware and software | M64: =IFERROR(__xludf.DUMMYFUNCTION("GOOGLETRANSLATE(F65, ""auto"", ""en"")"),"External intruder with an average potential intruder inner middle potential") -> External intruder with an average potential intruder inner middle potential | N64: =IFERROR(__xludf.DUMMYFUNCTION("GOOGLETRANSLATE(H65, ""auto"", ""en"")"),"System software, application software, network software, firmware, hardware,") -> System software, application software, network software, firmware, hardware,
J65: 64 | K65: =IFERROR(__xludf.DUMMYFUNCTION("GOOGLETRANSLATE(B66, ""auto"", ""en"")"),"The threat of incorrect implementation of the licensing policies in the cloud") -> The threat of incorrect implementation of the licensing policies in the cloud | L65: =IFERROR(__xludf.DUMMYFUNCTION("GOOGLETRANSLATE(D66, ""auto"", ""en"")"),"The threat is the possibility of failure of consumers to cloud services remote access to rented software (ie, there is a loss of availability SaaS cloud services) to the fault provider of cloud-based services. This threat is caused by insufficient study "&"of the licensing policy management problem using the software from different vendors in the cloud. Implementation of this threat can be provided that the policy of licensing the use of software based on limiting the number of its units or the number of i"&"ts users, and create a virtual machine with the licensed software used many times") -> The threat is the possibility of failure of consumers to cloud services remote access to rented software (ie, there is a loss of availability SaaS cloud services) to the fault provider of cloud-based services. This threat is caused by insufficient study of the licensing policy management problem using the software from different vendors in the cloud. Implementation of this threat can be provided that the policy of licensing the use of software based on limiting the number of its units or the number of its users, and create a virtual machine with the licensed software used many times | M65: =IFERROR(__xludf.DUMMYFUNCTION("GOOGLETRANSLATE(F66, ""auto"", ""en"")"),"External intruder low potential insider with a low potential") -> External intruder low potential insider with a low potential | N65: =IFERROR(__xludf.DUMMYFUNCTION("GOOGLETRANSLATE(H66, ""auto"", ""en"")"),"System software, application software, networking software") -> System software, application software, networking software
J66: 65 | K66: =IFERROR(__xludf.DUMMYFUNCTION("GOOGLETRANSLATE(B67, ""auto"", ""en"")"),"The threat of uncertainty in the distribution of responsibility between the roles in the cloud") -> The threat of uncertainty in the distribution of responsibility between the roles in the cloud | L66: =IFERROR(__xludf.DUMMYFUNCTION("GOOGLETRANSLATE(D67, ""auto"", ""en"")"),"The threat is the potential for significant differences between the supplier and the consumer cloud services on issues related to the definition of their rights and obligations in terms of information security. This threat is caused by lack of sufficient"&" set for the distribution of control measures of responsibility between the different roles of the data ownership, access control, support for cloud infrastructure, and so on. N. The possibility of realization of the threat is increased when using cloud "&"services provided by other suppliers (ie in the case of schemes providing cloud services with the participation of intermediaries)") -> The threat is the potential for significant differences between the supplier and the consumer cloud services on issues related to the definition of their rights and obligations in terms of information security. This threat is caused by lack of sufficient set for the distribution of control measures of responsibility between the different roles of the data ownership, access control, support for cloud infrastructure, and so on. N. The possibility of realization of the threat is increased when using cloud services provided by other suppliers (ie in the case of schemes providing cloud services with the participation of intermediaries) | M66: =IFERROR(__xludf.DUMMYFUNCTION("GOOGLETRANSLATE(F67, ""auto"", ""en"")"),"External intruder low potential insider with a low potential") -> External intruder low potential insider with a low potential | N66: =IFERROR(__xludf.DUMMYFUNCTION("GOOGLETRANSLATE(H67, ""auto"", ""en"")"),"System Software") -> System Software
J67: 66 | K67: =IFERROR(__xludf.DUMMYFUNCTION("GOOGLETRANSLATE(B68, ""auto"", ""en"")"),"The threat of uncertainty responsibility for the security of the cloud") -> The threat of uncertainty responsibility for the security of the cloud | L67: =IFERROR(__xludf.DUMMYFUNCTION("GOOGLETRANSLATE(D68, ""auto"", ""en"")"),"The threat is the possibility of failure of a number of measures to protect the information as a provider of cloud services, as well as their customer. This threat is caused by the lack of a clear division of responsibilities regarding the security of in"&"formation between the consumer and the supplier of cloud-based services. Implementation of this threat can be subject to failure of the documentary division of responsibilities between the parties involved in the delivery of cloud services, as well as th"&"e lack of documentary determining responsibility for failure to comply with safety requirements") -> The threat is the possibility of failure of a number of measures to protect the information as a provider of cloud services, as well as their customer. This threat is caused by the lack of a clear division of responsibilities regarding the security of information between the consumer and the supplier of cloud-based services. Implementation of this threat can be subject to failure of the documentary division of responsibilities between the parties involved in the delivery of cloud services, as well as the lack of documentary determining responsibility for failure to comply with safety requirements | M67: =IFERROR(__xludf.DUMMYFUNCTION("GOOGLETRANSLATE(F68, ""auto"", ""en"")"),"External intruder with a low potential") -> External intruder with a low potential | N67: =IFERROR(__xludf.DUMMYFUNCTION("GOOGLETRANSLATE(H68, ""auto"", ""en"")"),"cloud system") -> cloud system
J68: 67 | K68: =IFERROR(__xludf.DUMMYFUNCTION("GOOGLETRANSLATE(B69, ""auto"", ""en"")"),"The threat of unauthorized familiarization with the protected information") -> The threat of unauthorized familiarization with the protected information | L68: =IFERROR(__xludf.DUMMYFUNCTION("GOOGLETRANSLATE(D69, ""auto"", ""en"")"),"The threat is the possibility of accidental or deliberate misuse familiarize the user with information that is not intended for him, and to further its use in order to achieve their own or ask him by other persons (organizations) destructive purposes. Th"&"is threat is due to vulnerabilities access controls, errors in the configuration parameters of data resources or the lack thereof. Implementation of this threat does not imply the installation and use of a special offender malicious software. At the same"&" time familiarizing can be performed by viewing the information with other users of display screens, with the printed documents, by eavesdropping on conversations, and others.") -> The threat is the possibility of accidental or deliberate misuse familiarize the user with information that is not intended for him, and to further its use in order to achieve their own or ask him by other persons (organizations) destructive purposes. This threat is due to vulnerabilities access controls, errors in the configuration parameters of data resources or the lack thereof. Implementation of this threat does not imply the installation and use of a special offender malicious software. At the same time familiarizing can be performed by viewing the information with other users of display screens, with the printed documents, by eavesdropping on conversations, and others. | M68: =IFERROR(__xludf.DUMMYFUNCTION("GOOGLETRANSLATE(F69, ""auto"", ""en"")"),"Insider with a low potential") -> Insider with a low potential | N68: =IFERROR(__xludf.DUMMYFUNCTION("GOOGLETRANSLATE(H69, ""auto"", ""en"")"),"Hardware, media, the file system objects") -> Hardware, media, the file system objects
J69: 68 | K69: =IFERROR(__xludf.DUMMYFUNCTION("GOOGLETRANSLATE(B70, ""auto"", ""en"")"),"The threat of unauthorized / improper use of the interface with the application") -> The threat of unauthorized / improper use of the interface with the application | L69: =IFERROR(__xludf.DUMMYFUNCTION("GOOGLETRANSLATE(D70, ""auto"", ""en"")"),"The threat is the possibility of the perpetrator of a destructive impact on the API software to implement features not originally envisaged diskreditiruemym application (for example, the use of the debugging functions of the API composition). This threat"&" is caused by the presence of weaknesses in the mechanism of input validation and API commands used software. Implementation of this threat is possible in terms of having the offender access to the API and lack diskreditiruemogo application input validat"&"ion mechanism and teams") -> The threat is the possibility of the perpetrator of a destructive impact on the API software to implement features not originally envisaged diskreditiruemym application (for example, the use of the debugging functions of the API composition). This threat is caused by the presence of weaknesses in the mechanism of input validation and API commands used software. Implementation of this threat is possible in terms of having the offender access to the API and lack diskreditiruemogo application input validation mechanism and teams | M69: =IFERROR(__xludf.DUMMYFUNCTION("GOOGLETRANSLATE(F70, ""auto"", ""en"")"),"External intruder with an average potential intruder inner middle potential") -> External intruder with an average potential intruder inner middle potential | N69: =IFERROR(__xludf.DUMMYFUNCTION("GOOGLETRANSLATE(H70, ""auto"", ""en"")"),"System software, application software, network software, firmware, registry") -> System software, application software, network software, firmware, registry
J70: 69 | K70: =IFERROR(__xludf.DUMMYFUNCTION("GOOGLETRANSLATE(B71, ""auto"", ""en"")"),"The threat of unlawful actions in the communication channels") -> The threat of unlawful actions in the communication channels | L70: =IFERROR(__xludf.DUMMYFUNCTION("GOOGLETRANSLATE(D71, ""auto"", ""en"")"),"The threat lies in the possibility of making changes in the violator job network protocols by adding or removing data from the data stream in order to influence work diskreditiruemoy system or gain access to confidential information transmitted over the c"&"ommunication channel. This threat is caused by weakness of network protocols, is the lack of checking the integrity and authenticity of the data. Implementation of this threat can be provided of the intruder unauthorized access to the network traffic") -> The threat lies in the possibility of making changes in the violator job network protocols by adding or removing data from the data stream in order to influence work diskreditiruemoy system or gain access to confidential information transmitted over the communication channel. This threat is caused by weakness of network protocols, is the lack of checking the integrity and authenticity of the data. Implementation of this threat can be provided of the intruder unauthorized access to the network traffic | M70: =IFERROR(__xludf.DUMMYFUNCTION("GOOGLETRANSLATE(F71, ""auto"", ""en"")"),"External intruder with a low potential") -> External intruder with a low potential | N70: =IFERROR(__xludf.DUMMYFUNCTION("GOOGLETRANSLATE(H71, ""auto"", ""en"")"),"network traffic") -> network traffic
J71: 70 | K71: =IFERROR(__xludf.DUMMYFUNCTION("GOOGLETRANSLATE(B72, ""auto"", ""en"")"),"Continuous modernization of cloud infrastructure threat") -> Continuous modernization of cloud infrastructure threat | L71: =IFERROR(__xludf.DUMMYFUNCTION("GOOGLETRANSLATE(D72, ""auto"", ""en"")"),"The threat is the possibility of entering into the cloud system vulnerabilities and weaknesses together with the addition of new hardware or software. The system, considered as protected on the stage of putting it into operation, can no longer be consider"&"ed as such after its modernization. This threat stems from the fact that, firstly, the cloud providers offer the possibility of a consumer cloud service selection and (or) changing the original composition of the software cloud infrastructure in the prov"&"ision of such services and, secondly, under intense connection of new consumers upgrading cloud infrastructure can take place several times a year. Implementation of this threat is possible if the period until the next modernization does not exceed the p"&"eriod of the assessment requirements of safety compliance in the absence of cloud service management system and security (cloud management system)") -> The threat is the possibility of entering into the cloud system vulnerabilities and weaknesses together with the addition of new hardware or software. The system, considered as protected on the stage of putting it into operation, can no longer be considered as such after its modernization. This threat stems from the fact that, firstly, the cloud providers offer the possibility of a consumer cloud service selection and (or) changing the original composition of the software cloud infrastructure in the provision of such services and, secondly, under intense connection of new consumers upgrading cloud infrastructure can take place several times a year. Implementation of this threat is possible if the period until the next modernization does not exceed the period of the assessment requirements of safety compliance in the absence of cloud service management system and security (cloud management system) | M71: =IFERROR(__xludf.DUMMYFUNCTION("GOOGLETRANSLATE(F72, ""auto"", ""en"")"),"The inner middle potential violator") -> The inner middle potential violator | N71: =IFERROR(__xludf.DUMMYFUNCTION("GOOGLETRANSLATE(H72, ""auto"", ""en"")"),"cloud infrastructure") -> cloud infrastructure
J72: 71 | K72: =IFERROR(__xludf.DUMMYFUNCTION("GOOGLETRANSLATE(B73, ""auto"", ""en"")"),"The threat of unauthorized recovery of deleted information to be protected") -> The threat of unauthorized recovery of deleted information to be protected | L72: =IFERROR(__xludf.DUMMYFUNCTION("GOOGLETRANSLATE(D73, ""auto"", ""en"")"),"The threat lies in the possibility of direct access (access to the lower levels of the architecture with respect to the level of the operating system) to data stored in the machine storage medium, or data read from the recovery of residual information car"&"rier machine. This threat is due to weaknesses erased mechanism computer media - information, remote from the machine carrier, in most cases, can be restored. Implementation of this threat is possible under the following conditions: deleting informatio"&"n from the machine without the use of carrier occurred methods (methods, algorithms) guaranteed data erasure (e.g., physical destruction machine information storage medium); technological features of computer media do not lead to the guaranteed destructi"&"on of the information when receiving a command for erasing data; the information is not stored in a cryptographically transformed form") -> The threat lies in the possibility of direct access (access to the lower levels of the architecture with respect to the level of the operating system) to data stored in the machine storage medium, or data read from the recovery of residual information carrier machine. This threat is due to weaknesses erased mechanism computer media - information, remote from the machine carrier, in most cases, can be restored. Implementation of this threat is possible under the following conditions: deleting information from the machine without the use of carrier occurred methods (methods, algorithms) guaranteed data erasure (e.g., physical destruction machine information storage medium); technological features of computer media do not lead to the guaranteed destruction of the information when receiving a command for erasing data; the information is not stored in a cryptographically transformed form | M72: =IFERROR(__xludf.DUMMYFUNCTION("GOOGLETRANSLATE(F73, ""auto"", ""en"")"),"External intruder low potential insider with a low potential") -> External intruder low potential insider with a low potential | N72: =IFERROR(__xludf.DUMMYFUNCTION("GOOGLETRANSLATE(H73, ""auto"", ""en"")"),"Machine data carrier") -> Machine data carrier
J73: 72 | K73: =IFERROR(__xludf.DUMMYFUNCTION("GOOGLETRANSLATE(B74, ""auto"", ""en"")"),"The threat of unauthorized off or bypass the security mechanisms of the entries in the BIOS") -> The threat of unauthorized off or bypass the security mechanisms of the entries in the BIOS | L73: =IFERROR(__xludf.DUMMYFUNCTION("GOOGLETRANSLATE(D74, ""auto"", ""en"")"),"The threat is the possibility of introducing in the BIOS / UEFI malicious code after erroneous or malicious shutdown user BIOS / UEFI protection mechanism on the recording, and the ability to install an unsigned updates to bypass the protection mechanism "&"of the entries in the BIOS / UEFI. This threat is caused by weakness of measures on restricting access to the management of BIOS / UEFI protection mechanism on the recording, as well as vulnerability BIOS / UEFI update mechanism, resulting in a buffer ov"&"erflow. Implementation of this threat can be in one of the following conditions: off mechanism to protect BIOS / UEFI write; Successful exploitation of the vulnerability of the offender BIOS / UEFI update mechanism, which leads to a buffer overflow") -> The threat is the possibility of introducing in the BIOS / UEFI malicious code after erroneous or malicious shutdown user BIOS / UEFI protection mechanism on the recording, and the ability to install an unsigned updates to bypass the protection mechanism of the entries in the BIOS / UEFI. This threat is caused by weakness of measures on restricting access to the management of BIOS / UEFI protection mechanism on the recording, as well as vulnerability BIOS / UEFI update mechanism, resulting in a buffer overflow. Implementation of this threat can be in one of the following conditions: off mechanism to protect BIOS / UEFI write; Successful exploitation of the vulnerability of the offender BIOS / UEFI update mechanism, which leads to a buffer overflow | M73: =IFERROR(__xludf.DUMMYFUNCTION("GOOGLETRANSLATE(F74, ""auto"", ""en"")"),"Insider with a low potential") -> Insider with a low potential | N73: =IFERROR(__xludf.DUMMYFUNCTION("GOOGLETRANSLATE(H74, ""auto"", ""en"")"),"Firmware and BIOS / UEFI hardware") -> Firmware and BIOS / UEFI hardware
J74: 73 | K74: =IFERROR(__xludf.DUMMYFUNCTION("GOOGLETRANSLATE(B75, ""auto"", ""en"")"),"The threat of unauthorized access to the active and (or) a virtual passive and (or) the physical network equipment of physical and (or) a virtual network") -> The threat of unauthorized access to the active and (or) a virtual passive and (or) the physical network equipment of physical and (or) a virtual network | L74: =IFERROR(__xludf.DUMMYFUNCTION("GOOGLETRANSLATE(D75, ""auto"", ""en"")"),"The threat is the possibility of changing the algorithm of the malware software network equipment and (or) its setting parameters by exploiting the vulnerabilities of software and (or) the firmware of the specified equipment. This threat is due to the li"&"mited functionality (the presence of weaknesses) and active (or) a virtual passive and (or) the physical network equipment constituting the virtual infrastructure, the presence in the equipment of a fixed network address. Implementation of this threat ca"&"n be provided in the software for vulnerabilities, and (or) the firmware network equipment") -> The threat is the possibility of changing the algorithm of the malware software network equipment and (or) its setting parameters by exploiting the vulnerabilities of software and (or) the firmware of the specified equipment. This threat is due to the limited functionality (the presence of weaknesses) and active (or) a virtual passive and (or) the physical network equipment constituting the virtual infrastructure, the presence in the equipment of a fixed network address. Implementation of this threat can be provided in the software for vulnerabilities, and (or) the firmware network equipment | M74: =IFERROR(__xludf.DUMMYFUNCTION("GOOGLETRANSLATE(F75, ""auto"", ""en"")"),"External intruder with an average potential intruder inner middle potential") -> External intruder with an average potential intruder inner middle potential | N74: =IFERROR(__xludf.DUMMYFUNCTION("GOOGLETRANSLATE(H75, ""auto"", ""en"")"),"Network equipment, firmware, network software, virtual appliances") -> Network equipment, firmware, network software, virtual appliances
J75: 74 | K75: =IFERROR(__xludf.DUMMYFUNCTION("GOOGLETRANSLATE(B76, ""auto"", ""en"")"),"The threat of unauthorized access to the authentication information") -> The threat of unauthorized access to the authentication information | L75: =IFERROR(__xludf.DUMMYFUNCTION("GOOGLETRANSLATE(D76, ""auto"", ""en"")"),"The threat is the possibility of extracting passwords, usernames or other credentials of the computer's memory or stolen (copied) password files (including those stored in clear text) with computer media") -> The threat is the possibility of extracting passwords, usernames or other credentials of the computer's memory or stolen (copied) password files (including those stored in clear text) with computer media | M75: =IFERROR(__xludf.DUMMYFUNCTION("GOOGLETRANSLATE(F76, ""auto"", ""en"")"),"External intruder low potential insider with a low potential") -> External intruder low potential insider with a low potential | N75: =IFERROR(__xludf.DUMMYFUNCTION("GOOGLETRANSLATE(H76, ""auto"", ""en"")"),"System software, file system objects, user credentials, the registry, the machine storage media") -> System software, file system objects, user credentials, the registry, the machine storage media
J76: 75 | K76: =IFERROR(__xludf.DUMMYFUNCTION("GOOGLETRANSLATE(B77, ""auto"", ""en"")"),"The threat of unauthorized access to the virtual transmission channels") -> The threat of unauthorized access to the virtual transmission channels | L76: =IFERROR(__xludf.DUMMYFUNCTION("GOOGLETRANSLATE(D77, ""auto"", ""en"")"),"The threat is the possibility of unauthorized intruder interception traffic network nodes that are not available through network technologies other than network virtualization technology, through the improper use of such technologies. This threat is caus"&"ed by weaknesses flow controls, firewall and access control implemented in respect of network virtualization technologies (through which the virtual data channels are being built). Implementation of this threat is possible in the presence of the offender"&" to exercise the privileges of interaction with network virtualization") -> The threat is the possibility of unauthorized intruder interception traffic network nodes that are not available through network technologies other than network virtualization technology, through the improper use of such technologies. This threat is caused by weaknesses flow controls, firewall and access control implemented in respect of network virtualization technologies (through which the virtual data channels are being built). Implementation of this threat is possible in the presence of the offender to exercise the privileges of interaction with network virtualization | M76: =IFERROR(__xludf.DUMMYFUNCTION("GOOGLETRANSLATE(F77, ""auto"", ""en"")"),"External intruder low potential insider with a low potential") -> External intruder low potential insider with a low potential | N76: =IFERROR(__xludf.DUMMYFUNCTION("GOOGLETRANSLATE(H77, ""auto"", ""en"")"),"Network software, network traffic, virtual devices") -> Network software, network traffic, virtual devices
J77: 76 | K77: =IFERROR(__xludf.DUMMYFUNCTION("GOOGLETRANSLATE(B78, ""auto"", ""en"")"),"The threat of unauthorized access to the hypervisor of the virtual machine and (or) physical network") -> The threat of unauthorized access to the hypervisor of the virtual machine and (or) physical network | L77: =IFERROR(__xludf.DUMMYFUNCTION("GOOGLETRANSLATE(D78, ""auto"", ""en"")"),"The threat is the possibility of bringing the offender whole (if the hypervisor - a) or part (when multiple interacting hypervisors) virtual infrastructure in a state of ""denial of service"" by means of destructive software impact on the hypervisor from "&"running in he created a virtual environment, virtual machines, or of the impact on the hypervisor through its connection to the physical network connection. This threat is due to the presence of a plurality of interfaces and interactions between hypervis"&"or virtual machine and (or) the physical network vulnerability hypervisor and vulnerabilities of software and the limited functionality of the hardware used to ensure its efficiency. Implementation of this threat can be in one of the following cases: th"&"e presence of the offender privileges sufficient to effect the destructive impact of the software virtual machine; presence of active hypervisor interface interaction with the physical computer network") -> The threat is the possibility of bringing the offender whole (if the hypervisor - a) or part (when multiple interacting hypervisors) virtual infrastructure in a state of "denial of service" by means of destructive software impact on the hypervisor from running in he created a virtual environment, virtual machines, or of the impact on the hypervisor through its connection to the physical network connection. This threat is due to the presence of a plurality of interfaces and interactions between hypervisor virtual machine and (or) the physical network vulnerability hypervisor and vulnerabilities of software and the limited functionality of the hardware used to ensure its efficiency. Implementation of this threat can be in one of the following cases: the presence of the offender privileges sufficient to effect the destructive impact of the software virtual machine; presence of active hypervisor interface interaction with the physical computer network | M77: =IFERROR(__xludf.DUMMYFUNCTION("GOOGLETRANSLATE(F78, ""auto"", ""en"")"),"External intruder with an average potential intruder inner middle potential") -> External intruder with an average potential intruder inner middle potential | N77: =IFERROR(__xludf.DUMMYFUNCTION("GOOGLETRANSLATE(H78, ""auto"", ""en"")"),"hypervisor") -> hypervisor
J78: 77 | K78: =IFERROR(__xludf.DUMMYFUNCTION("GOOGLETRANSLATE(B79, ""auto"", ""en"")"),"The threat of unauthorized access to data outside of the reserved address space, including a dedicated virtual hardware") -> The threat of unauthorized access to data outside of the reserved address space, including a dedicated virtual hardware | L78: =IFERROR(__xludf.DUMMYFUNCTION("GOOGLETRANSLATE(D79, ""auto"", ""en"")"),"The threat is the possibility of violations of malicious program operating within a virtual machine, the integrity of its code and (or) other virtual machines, operating under the control of the same hypervisor, as well as change its parameters (their) se"&"ttings. This threat is due to the presence of software weaknesses hypervisor providing isolation address space used for storing not only the protected data and program code processing its programs, but also a program code that implements virtual hardware"&" (virtual processing apparatus, data storage and transmission) from unauthorized access by a malicious program operating within a virtual machine. Implementation of this threat can be subject to the successful implementation of unauthorized access by a m"&"alicious program operating within a virtual machine, the data stored outside the space reserved for the user data address space of the virtual machine") -> The threat is the possibility of violations of malicious program operating within a virtual machine, the integrity of its code and (or) other virtual machines, operating under the control of the same hypervisor, as well as change its parameters (their) settings. This threat is due to the presence of software weaknesses hypervisor providing isolation address space used for storing not only the protected data and program code processing its programs, but also a program code that implements virtual hardware (virtual processing apparatus, data storage and transmission) from unauthorized access by a malicious program operating within a virtual machine. Implementation of this threat can be subject to the successful implementation of unauthorized access by a malicious program operating within a virtual machine, the data stored outside the space reserved for the user data address space of the virtual machine | M78: =IFERROR(__xludf.DUMMYFUNCTION("GOOGLETRANSLATE(F79, ""auto"", ""en"")"),"External intruder with an average potential intruder inner middle potential") -> External intruder with an average potential intruder inner middle potential | N78: =IFERROR(__xludf.DUMMYFUNCTION("GOOGLETRANSLATE(H79, ""auto"", ""en"")"),"Server, a workstation, a virtual machine, hypervisor, machine information carrier metadata") -> Server, a workstation, a virtual machine, hypervisor, machine information carrier metadata
J79: 78 | K79: =IFERROR(__xludf.DUMMYFUNCTION("GOOGLETRANSLATE(B80, ""auto"", ""en"")"),"The threat of unauthorized access to protected virtual machines of the virtual and (or) the physical network") -> The threat of unauthorized access to protected virtual machines of the virtual and (or) the physical network | L79: =IFERROR(__xludf.DUMMYFUNCTION("GOOGLETRANSLATE(D80, ""auto"", ""en"")"),"The threat is the possibility of the offender destructive impact on software virtual machines from the virtual and (or) physical networks as a standard (non-virtual) network technology, as well as through network virtualization. This threat is due to the"&" presence of virtual machines and the network address to perform their interaction with other network entities. Implementation of this threat can be provided that the offender information on the network address of the virtual machine, as well as current "&"virtual machine activity at the time of the offender destructive effects software") -> The threat is the possibility of the offender destructive impact on software virtual machines from the virtual and (or) physical networks as a standard (non-virtual) network technology, as well as through network virtualization. This threat is due to the presence of virtual machines and the network address to perform their interaction with other network entities. Implementation of this threat can be provided that the offender information on the network address of the virtual machine, as well as current virtual machine activity at the time of the offender destructive effects software | M79: =IFERROR(__xludf.DUMMYFUNCTION("GOOGLETRANSLATE(F80, ""auto"", ""en"")"),"External intruder low potential insider with a low potential") -> External intruder low potential insider with a low potential | N79: =IFERROR(__xludf.DUMMYFUNCTION("GOOGLETRANSLATE(H80, ""auto"", ""en"")"),"Virtual machine") -> Virtual machine
J80: 79 | K80: =IFERROR(__xludf.DUMMYFUNCTION("GOOGLETRANSLATE(B81, ""auto"", ""en"")"),"The threat of unauthorized access to the protected VMs from other VMs") -> The threat of unauthorized access to the protected VMs from other VMs | L80: =IFERROR(__xludf.DUMMYFUNCTION("GOOGLETRANSLATE(D81, ""auto"", ""en"")"),"The threat is the possibility of a destructive impact on the software protects virtual machines from other virtual machines using different communication mechanisms between virtual machines, hypervisor implemented and activated on the system. This threat"&" is due to weaknesses exchange mechanisms between virtual machines and the vulnerability of its implementation in a particular hypervisor. Implementation of this threat is possible on condition that the intruder privileges sufficient to use different com"&"munication mechanisms between virtual machines, implemented in hypervisor and activated in the system") -> The threat is the possibility of a destructive impact on the software protects virtual machines from other virtual machines using different communication mechanisms between virtual machines, hypervisor implemented and activated on the system. This threat is due to weaknesses exchange mechanisms between virtual machines and the vulnerability of its implementation in a particular hypervisor. Implementation of this threat is possible on condition that the intruder privileges sufficient to use different communication mechanisms between virtual machines, implemented in hypervisor and activated in the system | M80: =IFERROR(__xludf.DUMMYFUNCTION("GOOGLETRANSLATE(F81, ""auto"", ""en"")"),"External intruder low potential insider with a low potential") -> External intruder low potential insider with a low potential | N80: =IFERROR(__xludf.DUMMYFUNCTION("GOOGLETRANSLATE(H81, ""auto"", ""en"")"),"Virtual machine") -> Virtual machine
J81: 80 | K81: =IFERROR(__xludf.DUMMYFUNCTION("GOOGLETRANSLATE(B82, ""auto"", ""en"")"),"The threat of unauthorized access to protected virtual device from the virtual and (or) the physical network") -> The threat of unauthorized access to protected virtual device from the virtual and (or) the physical network | L81: =IFERROR(__xludf.DUMMYFUNCTION("GOOGLETRANSLATE(D82, ""auto"", ""en"")"),"The threat lies in the possibility of remote intruder unauthorized access to the virtual devices of the virtual and (or) the physical network via various network technologies used for data exchange in a system constructed with the use of virtualization te"&"chnologies. This threat is due to weaknesses in the presence of network interfaces of the hypervisor software intended for remote control over the composition and configuration of virtual devices created (generated) data hypervisors. Implementation of t"&"his threat is possible on condition that the intruder sufficient privileges to perform data exchange in a system constructed with the use of virtualization") -> The threat lies in the possibility of remote intruder unauthorized access to the virtual devices of the virtual and (or) the physical network via various network technologies used for data exchange in a system constructed with the use of virtualization technologies. This threat is due to weaknesses in the presence of network interfaces of the hypervisor software intended for remote control over the composition and configuration of virtual devices created (generated) data hypervisors. Implementation of this threat is possible on condition that the intruder sufficient privileges to perform data exchange in a system constructed with the use of virtualization | M81: =IFERROR(__xludf.DUMMYFUNCTION("GOOGLETRANSLATE(F82, ""auto"", ""en"")"),"External intruder with an average potential intruder inner middle potential") -> External intruder with an average potential intruder inner middle potential | N81: =IFERROR(__xludf.DUMMYFUNCTION("GOOGLETRANSLATE(H82, ""auto"", ""en"")"),"Virtual storage devices, data processing and transmission") -> Virtual storage devices, data processing and transmission
J82: 81 | K82: =IFERROR(__xludf.DUMMYFUNCTION("GOOGLETRANSLATE(B83, ""auto"", ""en"")"),"The threat of unauthorized access to the local computer through a customer's grid system") -> The threat of unauthorized access to the local computer through a customer's grid system | L82: =IFERROR(__xludf.DUMMYFUNCTION("GOOGLETRANSLATE(D83, ""auto"", ""en"")"),"The threat lies in the possibility of the intruder network access the grid system assembly with the rights of one user accounts corresponding software processes job management system, followed by obtaining access to the restricted part of cryptographic ce"&"rtificates used for communication in the grid system. This threat is due to vulnerabilities on the client grid system (client software to be installed at the nodes of the grid system), operation of which allows an attacker to perform read and write opera"&"tions in a computer local file system objects sending software processes signals (including signals termination operation) read and write operations to the memory of program processes the corresponding communications software and grid jobs, opening networ"&"k connections to local and remote nodes grid system. Implementation of this threat can be subject to the implementation of malicious code in the job control system. In fact, the presence in the grid system node unknown to the owner of software (client gr"&"id system), the conductive unknown computation is a ""black box,"" through which (by exploitation of vulnerabilities or software bookmarks) the intruder may make illegal actions with respect to the stored node Grid system protected information (personal i"&"nformation site owner)") -> The threat lies in the possibility of the intruder network access the grid system assembly with the rights of one user accounts corresponding software processes job management system, followed by obtaining access to the restricted part of cryptographic certificates used for communication in the grid system. This threat is due to vulnerabilities on the client grid system (client software to be installed at the nodes of the grid system), operation of which allows an attacker to perform read and write operations in a computer local file system objects sending software processes signals (including signals termination operation) read and write operations to the memory of program processes the corresponding communications software and grid jobs, opening network connections to local and remote nodes grid system. Implementation of this threat can be subject to the implementation of malicious code in the job control system. In fact, the presence in the grid system node unknown to the owner of software (client grid system), the conductive unknown computation is a "black box," through which (by exploitation of vulnerabilities or software bookmarks) the intruder may make illegal actions with respect to the stored node Grid system protected information (personal information site owner) | M82: =IFERROR(__xludf.DUMMYFUNCTION("GOOGLETRANSLATE(F83, ""auto"", ""en"")"),"The outer middle potential violator") -> The outer middle potential violator | N82: =IFERROR(__xludf.DUMMYFUNCTION("GOOGLETRANSLATE(H83, ""auto"", ""en"")"),"Nodes grid system") -> Nodes grid system
J83: 82 | K83: =IFERROR(__xludf.DUMMYFUNCTION("GOOGLETRANSLATE(B84, ""auto"", ""en"")"),"The threat of unauthorized access to the computing field segments") -> The threat of unauthorized access to the computing field segments | L83: =IFERROR(__xludf.DUMMYFUNCTION("GOOGLETRANSLATE(D84, ""auto"", ""en"")"),"The threat is the possibility of unauthorized access to the offending source data, intermediate and final results of the calculations of other users of a supercomputer, as well as accidental or deliberate destructive influence decision processes some prob"&"lems on the processes and results of the decisions of other computing tasks. This threat is caused by weakness of subjects of access control mechanism to segments of computing fields supercomputer. Implementation of this threat is possible in the perfor"&"mance of tasks of different users on the same supercomputer computing supercomputer field") -> The threat is the possibility of unauthorized access to the offending source data, intermediate and final results of the calculations of other users of a supercomputer, as well as accidental or deliberate destructive influence decision processes some problems on the processes and results of the decisions of other computing tasks. This threat is caused by weakness of subjects of access control mechanism to segments of computing fields supercomputer. Implementation of this threat is possible in the performance of tasks of different users on the same supercomputer computing supercomputer field | M83: =IFERROR(__xludf.DUMMYFUNCTION("GOOGLETRANSLATE(F84, ""auto"", ""en"")"),"The inner middle potential violator") -> The inner middle potential violator | N83: =IFERROR(__xludf.DUMMYFUNCTION("GOOGLETRANSLATE(H84, ""auto"", ""en"")"),"Computing node supercomputer") -> Computing node supercomputer
J84: 83 | K84: =IFERROR(__xludf.DUMMYFUNCTION("GOOGLETRANSLATE(B85, ""auto"", ""en"")"),"The threat of unauthorized access to the system wirelessly") -> The threat of unauthorized access to the system wirelessly | L84: =IFERROR(__xludf.DUMMYFUNCTION("GOOGLETRANSLATE(D85, ""auto"", ""en"")"),"The threat is the possibility of obtaining the offender access to the resources of the whole information system through diskreditiruemoy used in its composition of wireless data channels. This threat is due to weaknesses identification / authentication p"&"rotocols (such as WEP, WPA and WPA2, AES), used for access to the wireless equipment. Implementation of this threat is possible on condition that the intruder specialized software that implements the functions of manual identification / wireless authenti"&"cation protocol vulnerabilities, and finding a reception point diskreditiruemoy wireless signals") -> The threat is the possibility of obtaining the offender access to the resources of the whole information system through diskreditiruemoy used in its composition of wireless data channels. This threat is due to weaknesses identification / authentication protocols (such as WEP, WPA and WPA2, AES), used for access to the wireless equipment. Implementation of this threat is possible on condition that the intruder specialized software that implements the functions of manual identification / wireless authentication protocol vulnerabilities, and finding a reception point diskreditiruemoy wireless signals | M84: =IFERROR(__xludf.DUMMYFUNCTION("GOOGLETRANSLATE(F85, ""auto"", ""en"")"),"External intruder with a low potential") -> External intruder with a low potential | N84: =IFERROR(__xludf.DUMMYFUNCTION("GOOGLETRANSLATE(H85, ""auto"", ""en"")"),"Network node, user credentials, network traffic, hardware") -> Network node, user credentials, network traffic, hardware
J85: 84 | K85: =IFERROR(__xludf.DUMMYFUNCTION("GOOGLETRANSLATE(B86, ""auto"", ""en"")"),"The threat of unauthorized access to the data from the virtual storage system and (or) the physical network") -> The threat of unauthorized access to the data from the virtual storage system and (or) the physical network | L85: =IFERROR(__xludf.DUMMYFUNCTION("GOOGLETRANSLATE(D86, ""auto"", ""en"")"),"The threat lies in the possibility of destructive software impact to virtual data storage devices, and (or) the virtual disks (which are both the segments of the virtual disk space created by a separate virtual device, and a single virtual disk space crea"&"ted by the logical association of multiple virtual data storage devices). This threat is due to the presence of weaknesses applied to various virtual data storage devices of information distribution techniques and (or) the virtual disk, as well as techno"&"logy weaknesses single virtual space. These weaknesses are related to the high complexity of ensuring coherence of information distribution algorithms within a single virtual space and interact with virtual and physical data channels for operation within "&"a single storage space. Implementation of this threat is possible on condition that the intruder special software able to exploit weaknesses of the technologies used in the construction of storage systems (network technology, information distribution tec"&"hnologies, etc.).") -> The threat lies in the possibility of destructive software impact to virtual data storage devices, and (or) the virtual disks (which are both the segments of the virtual disk space created by a separate virtual device, and a single virtual disk space created by the logical association of multiple virtual data storage devices). This threat is due to the presence of weaknesses applied to various virtual data storage devices of information distribution techniques and (or) the virtual disk, as well as technology weaknesses single virtual space. These weaknesses are related to the high complexity of ensuring coherence of information distribution algorithms within a single virtual space and interact with virtual and physical data channels for operation within a single storage space. Implementation of this threat is possible on condition that the intruder special software able to exploit weaknesses of the technologies used in the construction of storage systems (network technology, information distribution technologies, etc.). | M85: =IFERROR(__xludf.DUMMYFUNCTION("GOOGLETRANSLATE(F86, ""auto"", ""en"")"),"External intruder low potential insider with a low potential") -> External intruder low potential insider with a low potential | N85: =IFERROR(__xludf.DUMMYFUNCTION("GOOGLETRANSLATE(H86, ""auto"", ""en"")"),"Virtual storage devices, virtual disks") -> Virtual storage devices, virtual disks
J86: 85 | K86: =IFERROR(__xludf.DUMMYFUNCTION("GOOGLETRANSLATE(B87, ""auto"", ""en"")"),"The threat of unauthorized access to stored in the virtual space of information to be protected") -> The threat of unauthorized access to stored in the virtual space of information to be protected | L86: =IFERROR(__xludf.DUMMYFUNCTION("GOOGLETRANSLATE(D87, ""auto"", ""en"")"),"The threat is the possibility of a breach of confidentiality of the information contained in the distributed files containing protected information, by restoring the data files distributed from their many separate fragments with the help of software and i"&"nformation technology for the distributed processing of the information. This threat is due to the fact that in connection with the use of a plurality of virtualization technologies designed to work with the data (data distribution within the virtual and"&" logical disk, the data distribution between such disks, the distribution of data between physical and virtual drives a single disc space, allocation areas of disk space in as separate drives and al.), virtually all of the files stored in a plurality of s"&"eparate segments. Implementation of this threat can be subject to failure or lack of measures to ensure the confidentiality of information stored on a separate drive") -> The threat is the possibility of a breach of confidentiality of the information contained in the distributed files containing protected information, by restoring the data files distributed from their many separate fragments with the help of software and information technology for the distributed processing of the information. This threat is due to the fact that in connection with the use of a plurality of virtualization technologies designed to work with the data (data distribution within the virtual and logical disk, the data distribution between such disks, the distribution of data between physical and virtual drives a single disc space, allocation areas of disk space in as separate drives and al.), virtually all of the files stored in a plurality of separate segments. Implementation of this threat can be subject to failure or lack of measures to ensure the confidentiality of information stored on a separate drive | M86: =IFERROR(__xludf.DUMMYFUNCTION("GOOGLETRANSLATE(F87, ""auto"", ""en"")"),"External intruder with an average potential intruder inner middle potential") -> External intruder with an average potential intruder inner middle potential | N86: =IFERROR(__xludf.DUMMYFUNCTION("GOOGLETRANSLATE(H87, ""auto"", ""en"")"),"the media, the file system objects") -> the media, the file system objects
J87: 86 | K87: =IFERROR(__xludf.DUMMYFUNCTION("GOOGLETRANSLATE(B88, ""auto"", ""en"")"),"The threat of unauthorized changes to the authentication information") -> The threat of unauthorized changes to the authentication information | L87: =IFERROR(__xludf.DUMMYFUNCTION("GOOGLETRANSLATE(D88, ""auto"", ""en"")"),"The threat is the possibility of unauthorized access to the perpetrator of the authentication information of other users by using standard means of operating system and special software. This threat is caused by the presence of the weaknesses of measures"&" restricting access to the authentication information. Implementation of this threat may contribute to the further penetration of the offender in the system under the account user discredited") -> The threat is the possibility of unauthorized access to the perpetrator of the authentication information of other users by using standard means of operating system and special software. This threat is caused by the presence of the weaknesses of measures restricting access to the authentication information. Implementation of this threat may contribute to the further penetration of the offender in the system under the account user discredited | M87: =IFERROR(__xludf.DUMMYFUNCTION("GOOGLETRANSLATE(F88, ""auto"", ""en"")"),"External intruder low potential insider with a low potential") -> External intruder low potential insider with a low potential | N87: =IFERROR(__xludf.DUMMYFUNCTION("GOOGLETRANSLATE(H88, ""auto"", ""en"")"),"System software, file system objects, user credentials, the registry") -> System software, file system objects, user credentials, the registry
J88: 87 | K88: =IFERROR(__xludf.DUMMYFUNCTION("GOOGLETRANSLATE(B89, ""auto"", ""en"")"),"The threat of unauthorized use of privileged BIOS functions") -> The threat of unauthorized use of privileged BIOS functions | L88: =IFERROR(__xludf.DUMMYFUNCTION("GOOGLETRANSLATE(D89, ""auto"", ""en"")"),"The threat is the possibility of the use of potentially dangerous offender BIOS / UEFI features. This threat is due to the presence in the BIOS / UEFI potentially hazardous functional") -> The threat is the possibility of the use of potentially dangerous offender BIOS / UEFI features. This threat is due to the presence in the BIOS / UEFI potentially hazardous functional | M88: =IFERROR(__xludf.DUMMYFUNCTION("GOOGLETRANSLATE(F89, ""auto"", ""en"")"),"External attackers with a high potential insider with a low potential") -> External attackers with a high potential insider with a low potential | N88: =IFERROR(__xludf.DUMMYFUNCTION("GOOGLETRANSLATE(H89, ""auto"", ""en"")"),"Hardware, firmware, BIOS / UEFI") -> Hardware, firmware, BIOS / UEFI
J89: 88 | K89: =IFERROR(__xludf.DUMMYFUNCTION("GOOGLETRANSLATE(B90, ""auto"", ""en"")"),"The threat of unauthorized copying of protected information") -> The threat of unauthorized copying of protected information | L89: =IFERROR(__xludf.DUMMYFUNCTION("GOOGLETRANSLATE(D90, ""auto"", ""en"")"),"The threat is the possibility of illegal acquisition of the offender a copy of protected information by carrying out a sequence of misconduct, including: unauthorized access to protected information, copy information found on removable media (or other loc"&"ation available violator outside the system). This threat is caused by weakness of mechanisms of differentiation of access to protected information and access control of persons in the controlled area. Implementation of this threat is possible in the ab"&"sence of cryptographic protection measures or make copies at the time of the processing of protected information unencrypted") -> The threat is the possibility of illegal acquisition of the offender a copy of protected information by carrying out a sequence of misconduct, including: unauthorized access to protected information, copy information found on removable media (or other location available violator outside the system). This threat is caused by weakness of mechanisms of differentiation of access to protected information and access control of persons in the controlled area. Implementation of this threat is possible in the absence of cryptographic protection measures or make copies at the time of the processing of protected information unencrypted | M89: =IFERROR(__xludf.DUMMYFUNCTION("GOOGLETRANSLATE(F90, ""auto"", ""en"")"),"External intruder low potential insider with a low potential") -> External intruder low potential insider with a low potential | N89: =IFERROR(__xludf.DUMMYFUNCTION("GOOGLETRANSLATE(H90, ""auto"", ""en"")"),"file system objects, machine storage media") -> file system objects, machine storage media
J90: 89 | K90: =IFERROR(__xludf.DUMMYFUNCTION("GOOGLETRANSLATE(B91, ""auto"", ""en"")"),"The threat of unauthorized editing registry") -> The threat of unauthorized editing registry | L90: =IFERROR(__xludf.DUMMYFUNCTION("GOOGLETRANSLATE(D91, ""auto"", ""en"")"),"The threat is the possibility of making changes to the offender used diskreditiruemym application registry that affect the functioning of certain applications or application services as a whole. In this case, under the registry is meant not only the regis"&"try Microsoft Windows operating system, and any registry used by the application. Registry modification may be either in the implementation of another step of a destructive impact and the main purpose. This threat is caused by weakness of access control "&"mechanism is to assign implementing its programs is too high privileges when working with the registry. Implementation of this threat is possible in case of infringement of the rights to work with the program registry editing") -> The threat is the possibility of making changes to the offender used diskreditiruemym application registry that affect the functioning of certain applications or application services as a whole. In this case, under the registry is meant not only the registry Microsoft Windows operating system, and any registry used by the application. Registry modification may be either in the implementation of another step of a destructive impact and the main purpose. This threat is caused by weakness of access control mechanism is to assign implementing its programs is too high privileges when working with the registry. Implementation of this threat is possible in case of infringement of the rights to work with the program registry editing | M90: =IFERROR(__xludf.DUMMYFUNCTION("GOOGLETRANSLATE(F91, ""auto"", ""en"")"),"External intruder low potential insider with a low potential") -> External intruder low potential insider with a low potential | N90: =IFERROR(__xludf.DUMMYFUNCTION("GOOGLETRANSLATE(H91, ""auto"", ""en"")"),"System software using the registry, the registry") -> System software using the registry, the registry
J91: 90 | K91: =IFERROR(__xludf.DUMMYFUNCTION("GOOGLETRANSLATE(B92, ""auto"", ""en"")"),"The threat of unauthorized creation of a user account") -> The threat of unauthorized creation of a user account | L91: =IFERROR(__xludf.DUMMYFUNCTION("GOOGLETRANSLATE(D92, ""auto"", ""en"")"),"The threat is the possibility of creating the offender in the system more user account and its further use in their own illegal purposes (login with the rights of the account and of the destructive actions with respect to the discredited system or of the "&"discredited system in relation to other systems). This threat is caused by weakness of mechanisms of differentiation of access to the protected information. Implementation of this threat is possible in the case of rights and to launch special programs t"&"o edit files containing information about the users of the system (for remote access) or full-time access control of an operating system composition (local access)") -> The threat is the possibility of creating the offender in the system more user account and its further use in their own illegal purposes (login with the rights of the account and of the destructive actions with respect to the discredited system or of the discredited system in relation to other systems). This threat is caused by weakness of mechanisms of differentiation of access to the protected information. Implementation of this threat is possible in the case of rights and to launch special programs to edit files containing information about the users of the system (for remote access) or full-time access control of an operating system composition (local access) | M91: =IFERROR(__xludf.DUMMYFUNCTION("GOOGLETRANSLATE(F92, ""auto"", ""en"")"),"External intruder low potential insider with a low potential") -> External intruder low potential insider with a low potential | N91: =IFERROR(__xludf.DUMMYFUNCTION("GOOGLETRANSLATE(H92, ""auto"", ""en"")"),"System Software") -> System Software
J92: 91 | K92: =IFERROR(__xludf.DUMMYFUNCTION("GOOGLETRANSLATE(B93, ""auto"", ""en"")"),"The threat of unauthorized removal of protected information") -> The threat of unauthorized removal of protected information | L92: =IFERROR(__xludf.DUMMYFUNCTION("GOOGLETRANSLATE(D93, ""auto"", ""en"")"),"The threat is the possibility of causing the offender economic, informational, moral and other kinds of damage to the owner and the operator wrongly deleted information through the implementation of destructive software or physical impact on the native me"&"dia. This threat is due to the lack of measures to ensure access to the protected information in the system, as well, and the presence of vulnerabilities in the software that implements these measures. Implementation of this threat is possible in case o"&"f a system violator of rights to data erasure, or physical access to a machine-readable medium by a distance sufficient to provide an effective destructive impact") -> The threat is the possibility of causing the offender economic, informational, moral and other kinds of damage to the owner and the operator wrongly deleted information through the implementation of destructive software or physical impact on the native media. This threat is due to the lack of measures to ensure access to the protected information in the system, as well, and the presence of vulnerabilities in the software that implements these measures. Implementation of this threat is possible in case of a system violator of rights to data erasure, or physical access to a machine-readable medium by a distance sufficient to provide an effective destructive impact | M92: =IFERROR(__xludf.DUMMYFUNCTION("GOOGLETRANSLATE(F93, ""auto"", ""en"")"),"External intruder low potential insider with a low potential") -> External intruder low potential insider with a low potential | N92: =IFERROR(__xludf.DUMMYFUNCTION("GOOGLETRANSLATE(H93, ""auto"", ""en"")"),"The metadata file system objects, the registry") -> The metadata file system objects, the registry
J93: 92 | K93: =IFERROR(__xludf.DUMMYFUNCTION("GOOGLETRANSLATE(B94, ""auto"", ""en"")"),"The threat of unauthorized remote out of band access to hardware") -> The threat of unauthorized remote out of band access to hardware | L93: =IFERROR(__xludf.DUMMYFUNCTION("GOOGLETRANSLATE(D94, ""auto"", ""en"")"),"The threat is the possibility of obtaining the offender management system privileges by using the remote out of band (in-band independent TCP / IP) access. This threat is caused by the inability to control the mechanism that implements remote access func"&"tions in hardware, operating system level as well as the independence of the state of hardware devices, power supply, as This mechanism provides a procedure for remote on / off hardware devices. Implementation of this threat is possible in the circumstan"&"ces: the availability of the system hardware that supports out of band remote access technology; the availability of connecting the system to the public network (Internet)") -> The threat is the possibility of obtaining the offender management system privileges by using the remote out of band (in-band independent TCP / IP) access. This threat is caused by the inability to control the mechanism that implements remote access functions in hardware, operating system level as well as the independence of the state of hardware devices, power supply, as This mechanism provides a procedure for remote on / off hardware devices. Implementation of this threat is possible in the circumstances: the availability of the system hardware that supports out of band remote access technology; the availability of connecting the system to the public network (Internet) | M93: =IFERROR(__xludf.DUMMYFUNCTION("GOOGLETRANSLATE(F94, ""auto"", ""en"")"),"External intruder with a high potential") -> External intruder with a high potential | N93: =IFERROR(__xludf.DUMMYFUNCTION("GOOGLETRANSLATE(H94, ""auto"", ""en"")"),"Information system, hardware") -> Information system, hardware
J94: 93 | K94: =IFERROR(__xludf.DUMMYFUNCTION("GOOGLETRANSLATE(B95, ""auto"", ""en"")"),"The threat of unauthorized buffer management") -> The threat of unauthorized buffer management | L94: =IFERROR(__xludf.DUMMYFUNCTION("GOOGLETRANSLATE(D95, ""auto"", ""en"")"),"The threat is the possibility of wrongdoing unauthorized access to data contained in the clipboard, in the interests of acquaintance with information stored there, or destructive of the impact on the system software (e.g., a buffer overflow to execute arb"&"itrary malicious code). This threat is due to weakness in the mechanism of restricting access to the clipboard, and weaknesses in the input data verification mechanisms. Implementation of this threat is possible in case of unauthorized intruder successf"&"ul access to the segment memory diskreditiruemogo object, which is located in clipboard") -> The threat is the possibility of wrongdoing unauthorized access to data contained in the clipboard, in the interests of acquaintance with information stored there, or destructive of the impact on the system software (e.g., a buffer overflow to execute arbitrary malicious code). This threat is due to weakness in the mechanism of restricting access to the clipboard, and weaknesses in the input data verification mechanisms. Implementation of this threat is possible in case of unauthorized intruder successful access to the segment memory diskreditiruemogo object, which is located in clipboard | M94: =IFERROR(__xludf.DUMMYFUNCTION("GOOGLETRANSLATE(F95, ""auto"", ""en"")"),"External intruder low potential insider with a low potential") -> External intruder low potential insider with a low potential | N94: =IFERROR(__xludf.DUMMYFUNCTION("GOOGLETRANSLATE(H95, ""auto"", ""en"")"),"System software, application software, networking software") -> System software, application software, networking software
